Workbook

Sheet Profit and Loss Statement
E1: BORROWER_NAME
E2: BORROWER_CODE
A3: 8e28cb47-8f2a-4284-a118-9bff91643dd9 | E3: TEMPLATE_NAME | F3: Company Financial Template
E4: PROJECT_NAME
E5: ACCOUNTING_TYPE | F5: GAAP
E6: FINANCIAL_TYPE | F6: Consolidated
E7: YEAR | F7: =IF(F9="","",YEAR(F9)) | G7: =IF(G9="","",YEAR(G9)) | H7: =IF(H9="","",YEAR(H9)) | I7: =IF(I9="","",YEAR(I9)) | J7: =IF(J9="","",YEAR(J9)) | K7: =IF(K9="","",YEAR(K9)) | L7: =IF(L9="","",YEAR(L9)) | M7: =IF(M9="","",YEAR(M9)) | ... AI7: =IF(AI9="","",YEAR(AI9))
E8: YEAR_TYPE | F8: Audited
E9: STATEMENT_DATE (YYYY-MM-DD)
E10: NO_OF_MONTHS
E11: CURRENCY | F11: INR | G11: =F11 -> INR | H11: =G11 -> INR | I11: =H11 -> INR | J11: =I11 -> INR | K11: =J11 -> INR | L11: =K11 -> INR | M11: =L11 -> INR | N11: =M11 -> INR | ... AI11: =AH11 -> INR
E12: DENOMINATION | F12: Crores | G12: =F12 -> Crores | H12: =G12 -> Crores | I12: =H12 -> Crores | J12: =I12 -> Crores | K12: =J12 -> Crores | L12: =K12 -> Crores | M12: =L12 -> Crores | N12: =M12 -> Crores | ... AI12: =AH12 -> Crores
E13: AUDITOR_NAME
E14: VERSION
E15: CIF_ID
E16: BASE_YEAR
F17: 1 | G17: 2 | H17: 3 | I17: 4 | J17: 5 | K17: 6 | L17: 7 | M17: 8 | N17: 9 | O17: 10 | P17: 11 | Q17: 12 | R17: 13 | S17: 14 | T17: 15 | U17: 16 | V17: 17 | W17: 18 | X17: 19 | Y17: 20 | Z17: 21 | AA17: 22 | AB17: 23 | AC17: 24 | AD17: 25 | AE17: 26 | AF17: 27 | AG17: 28 | AH17: 29 | AI17: 30
A18: UUID | B18: PARENT ID | C18: AUTO_SEQUENCE | D18: INPUT_SEQUENCE | E18: LINE_ITEM_NAME | F18: VALUE | G18: VALUE | H18: VALUE | I18: VALUE | J18: VALUE | K18: VALUE | L18: VALUE | M18: VALUE | N18: VALUE | O18: VALUE | P18: VALUE | Q18: VALUE | R18: VALUE | S18: VALUE | T18: VALUE | U18: VALUE | V18: VALUE | W18: VALUE | X18: VALUE | Y18: VALUE | Z18: VALUE | AA18: VALUE | AB18: VALUE | AC18: VALUE | AD18: VALUE | AE18: VALUE | AF18: VALUE | AG18: VALUE | AH18: VALUE | AI18: VALUE
A19: c98dd930-c06b-4184-a258-ac39cd19a193 | C19: 1 | E19: Profit and Loss Statement
A20: 10a60949-9659-4ea4-b1c3-1f16074a2874 | B20: c98dd930-c06b-4184-a258-ac39cd19a193 | C20: 1.1 | D20: 1 | E20: Gross Sales
A21: 1fe0fddb-2578-4028-bb64-bd63d70cdd09 | B21: 10a60949-9659-4ea4-b1c3-1f16074a2874 | C21: 1.1.1 | D21: 1.1 | E21: Domestic Sales
A22: 725d10e1-e2a6-4996-b9d0-4ad6ffc75b68 | B22: 10a60949-9659-4ea4-b1c3-1f16074a2874 | C22: 1.1.2 | D22: 1.2 | E22: Export Sales
A23: 640dbfc9-deeb-44e3-9198-96949e0cae58 | B23: 10a60949-9659-4ea4-b1c3-1f16074a2874 | C23: 1.1.3 | D23: 1.3 | E23: Total | F23: =ROUND(SUM(F$21:F$22),2) -> 0 | G23: =ROUND(SUM(G$21:G$22),2) -> 0 | H23: =ROUND(SUM(H$21:H$22),2) -> 0 | I23: =ROUND(SUM(I$21:I$22),2) -> 0 | J23: =ROUND(SUM(J$21:J$22),2) -> 0 | K23: =ROUND(SUM(K$21:K$22),2) -> 0 | L23: =ROUND(SUM(L$21:L$22),2) -> 0 | M23: =ROUND(SUM(M$21:M$22),2) -> 0 | ... AI23: =ROUND(SUM(AI$21:AI$22),2) -> 0
A24: 59b1facc-2b05-4ef0-bd3c-52d6156b19af | B24: c98dd930-c06b-4184-a258-ac39cd19a193 | C24: 1.2 | D24: 2 | E24: Less Excise Duty
A25: a3c6e8f3-99c4-41a0-adec-acb5ff2f3b00 | B25: c98dd930-c06b-4184-a258-ac39cd19a193 | C25: 1.3 | D25: 3 | E25: Net Sales (1 - 2) | F25: =ROUND(F23-F24,2) -> 0 | G25: =ROUND(G23-G24,2) -> 0 | H25: =ROUND(H23-H24,2) -> 0 | I25: =ROUND(I23-I24,2) -> 0 | J25: =ROUND(J23-J24,2) -> 0 | K25: =ROUND(K23-K24,2) -> 0 | L25: =ROUND(L23-L24,2) -> 0 | M25: =ROUND(M23-M24,2) -> 0 | ... AI25: =ROUND(AI23-AI24,2) -> 0
A26: 48b561dd-2f32-4bf9-9890-f458e178e892 | B26: c98dd930-c06b-4184-a258-ac39cd19a193 | C26: 1.4 | E26: % age rise (+) or fall (-) in net sales as compared to previous year (annualised) | G26: =IF(F25=0,0,IF(G25=0,0,((G25/G10)-(F25/F10))/(F25/F10))*100) -> 0 | H26: =IF(G25=0,0,IF(H25=0,0,((H25/H10)-(G25/G10))/(G25/G10))*100) -> 0 | I26: =IF(H25=0,0,IF(I25=0,0,((I25/I10)-(H25/H10))/(H25/H10))*100) -> 0 | J26: =IF(I25=0,0,IF(J25=0,0,((J25/J10)-(I25/I10))/(I25/I10))*100) -> 0 | K26: =IF(J25=0,0,IF(K25=0,0,((K25/K10)-(J25/J10))/(J25/J10))*100) -> 0 | L26: =IF(K25=0,0,IF(L25=0,0,((L25/L10)-(K25/K10))/(K25/K10))*100) -> 0 | M26: =IF(L25=0,0,IF(M25=0,0,((M25/M10)-(L25/L10))/(L25/L10))*100) -> 0 | N26: =IF(M25=0,0,IF(N25=0,0,((N25/N10)-(M25/M10))/(M25/M10))*100) -> 0 | ... AI26: =IF(AH25=0,0,IF(AI25=0,0,((AI25/AI10)-(AH25/AH10))/(AH25/AH10))*100) -> 0
A27: 16c1b0ac-ba37-4ed6-bb75-c0d4993e9ae8 | B27: c98dd930-c06b-4184-a258-ac39cd19a193 | C27: 1.5 | E27: Other recurring income incidental to main business
A28: 758d688a-abd2-4efa-bace-54c0f837efaa | B28: c98dd930-c06b-4184-a258-ac39cd19a193 | C28: 1.6 | D28: 4 | E28: Total operating income | F28: =F25+F27 -> 0 | G28: =G25+G27 -> 0 | H28: =H25+H27 -> 0 | I28: =I25+I27 -> 0 | J28: =J25+J27 -> 0 | K28: =K25+K27 -> 0 | L28: =L25+L27 -> 0 | M28: =M25+M27 -> 0 | ... AI28: =AI25+AI27 -> 0
A29: 03e7d409-963e-4698-9508-323cb4718bd7 | B29: c98dd930-c06b-4184-a258-ac39cd19a193 | C29: 1.7 | D29: 5 | E29: Cost of Sales
A30: 3d4377af-5b9d-4fc5-8ad3-56f2be931ed3 | B30: 03e7d409-963e-4698-9508-323cb4718bd7 | C30: 1.7.1 | D30: i. | E30: Raw materials | F30: =ROUND(SUM(F$31:F$32),2) -> 0 | G30: =ROUND(SUM(G$31:G$32),2) -> 0 | H30: =ROUND(SUM(H$31:H$32),2) -> 0 | I30: =ROUND(SUM(I$31:I$32),2) -> 0 | J30: =ROUND(SUM(J$31:J$32),2) -> 0 | K30: =ROUND(SUM(K$31:K$32),2) -> 0 | L30: =ROUND(SUM(L$31:L$32),2) -> 0 | M30: =ROUND(SUM(M$31:M$32),2) -> 0 | ... AI30: =ROUND(SUM(AI$31:AI$32),2) -> 0
A31: d4fd265c-aebb-4d35-8d34-fbb90f8879b1 | B31: 3d4377af-5b9d-4fc5-8ad3-56f2be931ed3 | C31: 1.7.1.1 | D31: a. | E31: i) Imported
A32: 196afb1b-3271-4e26-8c17-a1687f1442a1 | B32: 3d4377af-5b9d-4fc5-8ad3-56f2be931ed3 | C32: 1.7.1.2 | D32: b. | E32: ii) Indigenous
A33: b5374b98-fbc9-4afd-91a6-687949a4353a | B33: 03e7d409-963e-4698-9508-323cb4718bd7 | C33: 1.7.2 | D33: ii. | E33: Other Spares
A34: f78f861b-e42f-4c79-b4df-5106e411ae92 | B34: 03e7d409-963e-4698-9508-323cb4718bd7 | C34: 1.7.3 | D34: iii. | E34: Power and Fuel
A35: 148302c9-c702-4281-9fb6-424bb1a09513 | B35: 03e7d409-963e-4698-9508-323cb4718bd7 | C35: 1.7.4 | D35: iv. | E35: Direct Labour (Factory wages & salaries)
A36: a8cd1b47-c726-4920-a36e-c957dd5e4e35 | B36: 03e7d409-963e-4698-9508-323cb4718bd7 | C36: 1.7.5 | D36: v. | E36: Other manufacturing expenses | F36: =ROUND(SUM(F$37:F$39),2) -> 0 | G36: =ROUND(SUM(G$37:G$39),2) -> 0 | H36: =ROUND(SUM(H$37:H$39),2) -> 0 | I36: =ROUND(SUM(I$37:I$39),2) -> 0 | J36: =ROUND(SUM(J$37:J$39),2) -> 0 | K36: =ROUND(SUM(K$37:K$39),2) -> 0 | L36: =ROUND(SUM(L$37:L$39),2) -> 0 | M36: =ROUND(SUM(M$37:M$39),2) -> 0 | ... AI36: =ROUND(SUM(AI$37:AI$39),2) -> 0
A37: 668ded41-a4aa-46a3-9c6a-800d00837629 | B37: a8cd1b47-c726-4920-a36e-c957dd5e4e35 | C37: 1.7.5.1 | D37: a. | E37: Processing / Job Work Charges
A38: 0ad52017-0aff-4518-ab1c-4f3090d51d34 | B38: a8cd1b47-c726-4920-a36e-c957dd5e4e35 | C38: 1.7.5.2 | D38: b. | E38: Freight and Transportation Charges
A39: 4920a1ca-7f77-41b8-b737-00b8b1672a4b | B39: a8cd1b47-c726-4920-a36e-c957dd5e4e35 | C39: 1.7.5.3 | D39: c. | E39: Others
A40: 0fe0bf01-2780-473f-9a02-0a0192c5ff6c | B40: 03e7d409-963e-4698-9508-323cb4718bd7 | C40: 1.7.6 | D40: vi a. | E40: Depreciation
A41: 2ac2e554-12a8-4d5f-a550-f4d76440b480 | B41: 03e7d409-963e-4698-9508-323cb4718bd7 | C41: 1.7.7 | D41: vi b. | E41: Amortization
A42: 1355a8e0-0532-4764-aaf9-5bcf329b1f83 | B42: 03e7d409-963e-4698-9508-323cb4718bd7 | C42: 1.7.8 | D42: vii | E42: Changes in inventory
A43: 36b81d10-11d4-409b-ab6a-458f6aee2219 | B43: 03e7d409-963e-4698-9508-323cb4718bd7 | C43: 1.7.9 | D43: viii. | E43: Sub-total (Total Cost of Sales) | F43: =ROUND(F34+F35+F42+F41+F40+F30+F33+F36,2) -> 0 | G43: =ROUND(G34+G35+G42+G41+G40+G30+G33+G36,2) -> 0 | H43: =ROUND(H34+H35+H42+H41+H40+H30+H33+H36,2) -> 0 | I43: =ROUND(I34+I35+I42+I41+I40+I30+I33+I36,2) -> 0 | J43: =ROUND(J34+J35+J42+J41+J40+J30+J33+J36,2) -> 0 | K43: =ROUND(K34+K35+K42+K41+K40+K30+K33+K36,2) -> 0 | L43: =ROUND(L34+L35+L42+L41+L40+L30+L33+L36,2) -> 0 | M43: =ROUND(M34+M35+M42+M41+M40+M30+M33+M36,2) -> 0 | ... AI43: =ROUND(AI34+AI35+AI42+AI41+AI40+AI30+AI33+AI36,2) -> 0
A44: d45d21cc-efc2-48d8-9d50-f166592f07f1 | B44: c98dd930-c06b-4184-a258-ac39cd19a193 | C44: 1.8 | D44: 6 | E44: Selling, general and administrative expenses | F44: =ROUND(SUM(F$45:F$55),2) -> 0 | G44: =ROUND(SUM(G$45:G$55),2) -> 0 | H44: =ROUND(SUM(H$45:H$55),2) -> 0 | I44: =ROUND(SUM(I$45:I$55),2) -> 0 | J44: =ROUND(SUM(J$45:J$55),2) -> 0 | K44: =ROUND(SUM(K$45:K$55),2) -> 0 | L44: =ROUND(SUM(L$45:L$55),2) -> 0 | M44: =ROUND(SUM(M$45:M$55),2) -> 0 | ... AI44: =ROUND(SUM(AI$45:AI$55),2) -> 0
A45: 2ef29c6a-8a7b-40e5-99c8-f89d9057243d | B45: d45d21cc-efc2-48d8-9d50-f166592f07f1 | C45: 1.8.1 | D45: a. | E45: Salary and staff expenses
A46: 2b68097c-b2d9-4814-b640-8029f0ca3ee4 | B46: d45d21cc-efc2-48d8-9d50-f166592f07f1 | C46: 1.8.2 | D46: b. | E46: Rent , Rates and Taxes
A47: 92aa2ec4-8a3c-4dbd-a197-ac3010cfc6d0 | B47: d45d21cc-efc2-48d8-9d50-f166592f07f1 | C47: 1.8.3 | D47: c. | E47: Lease rentals
A48: 70247812-1813-4670-b601-64da36a5258c | B48: d45d21cc-efc2-48d8-9d50-f166592f07f1 | C48: 1.8.4 | D48: d. | E48: Bad Debts
A49: 95e087db-f388-4a0a-9b9c-a87952212d64 | B49: d45d21cc-efc2-48d8-9d50-f166592f07f1 | C49: 1.8.5 | D49: e. | E49: Travelling & conveyance expenses
A50: 5a538d85-7501-4bcb-9624-8aebed73725d | B50: d45d21cc-efc2-48d8-9d50-f166592f07f1 | C50: 1.8.6 | D50: f. | E50: Advertisements and Sales Promotions
A51: f67c6972-1353-40e1-bcd7-1f1677bb7d3f | B51: d45d21cc-efc2-48d8-9d50-f166592f07f1 | C51: 1.8.7 | D51: g. | E51: Commission, discount & service charges
A52: 1863177f-a897-4a90-9a52-cc92f1986683 | B52: d45d21cc-efc2-48d8-9d50-f166592f07f1 | C52: 1.8.8 | D52: h. | E52: Legal & professional charges
A53: b5e1aae4-d350-417d-b95a-0c414c79e8e4 | B53: d45d21cc-efc2-48d8-9d50-f166592f07f1 | C53: 1.8.9 | D53: i. | E53: Directors remuneration
A54: 09c75130-6fcc-4aba-8999-33139f25d705 | B54: d45d21cc-efc2-48d8-9d50-f166592f07f1 | C54: 1.8.10 | D54: i. | E54: Auditors remuneration
A55: a8430eea-7c67-48ef-a1fb-72efd678b52b | B55: d45d21cc-efc2-48d8-9d50-f166592f07f1 | C55: 1.8.11 | D55: k | E55: Others
A56: 09ff9a1a-9720-422c-92fa-c3452fe2a4ed | B56: c98dd930-c06b-4184-a258-ac39cd19a193 | C56: 1.9 | D56: 7 | E56: Sub-total (5 + 6) | F56: =ROUND(F43+F44,2) -> 0 | G56: =ROUND(G43+G44,2) -> 0 | H56: =ROUND(H43+H44,2) -> 0 | I56: =ROUND(I43+I44,2) -> 0 | J56: =ROUND(J43+J44,2) -> 0 | K56: =ROUND(K43+K44,2) -> 0 | L56: =ROUND(L43+L44,2) -> 0 | M56: =ROUND(M43+M44,2) -> 0 | ... AI56: =ROUND(AI43+AI44,2) -> 0
A57: cd32dec1-9487-4fad-b68d-84929baa6c70 | B57: c98dd930-c06b-4184-a258-ac39cd19a193 | C57: 1.10 | D57: 8 | E57: Operating Profit before Interest (3 - 7) | F57: =ROUND(F28-F56,2) -> 0 | G57: =ROUND(G28-G56,2) -> 0 | H57: =ROUND(H28-H56,2) -> 0 | I57: =ROUND(I28-I56,2) -> 0 | J57: =ROUND(J28-J56,2) -> 0 | K57: =ROUND(K28-K56,2) -> 0 | L57: =ROUND(L28-L56,2) -> 0 | M57: =ROUND(M28-M56,2) -> 0 | ... AI57: =ROUND(AI28-AI56,2) -> 0
A58: 3c191bb5-9e45-49e9-92d8-62eac4a46fee | B58: c98dd930-c06b-4184-a258-ac39cd19a193 | C58: 1.11 | D58: 9 | E58: Interest | F58: =ROUND(SUM(F$59:F$61),2) -> 0 | G58: =ROUND(SUM(G$59:G$61),2) -> 0 | H58: =ROUND(SUM(H$59:H$61),2) -> 0 | I58: =ROUND(SUM(I$59:I$61),2) -> 0 | J58: =ROUND(SUM(J$59:J$61),2) -> 0 | K58: =ROUND(SUM(K$59:K$61),2) -> 0 | L58: =ROUND(SUM(L$59:L$61),2) -> 0 | M58: =ROUND(SUM(M$59:M$61),2) -> 0 | ... AI58: =ROUND(SUM(AI$59:AI$61),2) -> 0
A59: 4ac021e9-a288-49cb-8065-f08ce0d20a4b | B59: 3c191bb5-9e45-49e9-92d8-62eac4a46fee | C59: 1.11.1 | D59: a. | E59: Interest on Fixed Loans / Term loans
A60: 9d8baeb0-9b8d-4484-a719-47c3465e519d | B60: 3c191bb5-9e45-49e9-92d8-62eac4a46fee | C60: 1.11.2 | D60: b. | E60: Interest on Working capital loans
A61: 69206450-c21c-435c-ad96-06f800c1faee | B61: 3c191bb5-9e45-49e9-92d8-62eac4a46fee | C61: 1.11.3 | D61: c. | E61: Bank charges
A62: ef40fe86-94a1-411c-939f-2c4630b12982 | B62: c98dd930-c06b-4184-a258-ac39cd19a193 | C62: 1.12 | D62: 10 | E62: Operating Profit after Interest (8 - 9) | F62: =ROUND(F57-F58,2) -> 0 | G62: =ROUND(G57-G58,2) -> 0 | H62: =ROUND(H57-H58,2) -> 0 | I62: =ROUND(I57-I58,2) -> 0 | J62: =ROUND(J57-J58,2) -> 0 | K62: =ROUND(K57-K58,2) -> 0 | L62: =ROUND(L57-L58,2) -> 0 | M62: =ROUND(M57-M58,2) -> 0 | ... AI62: =ROUND(AI57-AI58,2) -> 0
A63: 1da9011e-e747-4ddc-a385-ab468c3d2848 | B63: c98dd930-c06b-4184-a258-ac39cd19a193 | C63: 1.13 | D63: 11 | E63: Add: Other non-operating Income
A64: 7922b178-da65-4ac7-9731-fd221f980f61 | B64: c98dd930-c06b-4184-a258-ac39cd19a193 | C64: 1.14 | D64: i. | E64: CASH ITEMS
A65: 73dec465-413e-426d-a2cc-dafce9007d2f | B65: 7922b178-da65-4ac7-9731-fd221f980f61 | C65: 1.14.1 | D65: a. | E65: Interest received
A66: 3c9cb6ec-b0b9-429e-8fb6-cf30cf358322 | B66: 7922b178-da65-4ac7-9731-fd221f980f61 | C66: 1.14.2 | D66: b. | E66: Dividends received from Companies
A67: f5404e9a-501d-4beb-8c52-a66cf3f2809c | B67: 7922b178-da65-4ac7-9731-fd221f980f61 | C67: 1.14.3 | D67: c | E67: Profit on sale of fixed assets / Investments
A68: ef45beb9-e0f1-4a75-ac2e-cd6ec751b34f | B68: 7922b178-da65-4ac7-9731-fd221f980f61 | C68: 1.14.4 | D68: d | E68: Misc Income
A69: 00fb8424-56dd-4bba-ab26-a02941464019 | B69: 7922b178-da65-4ac7-9731-fd221f980f61 | C69: 1.14.5 | E69: Sub-total (Non operating income - Cash) | F69: =ROUND(SUM(F$65:F$68),2) -> 0 | G69: =ROUND(SUM(G$65:G$68),2) -> 0 | H69: =ROUND(SUM(H$65:H$68),2) -> 0 | I69: =ROUND(SUM(I$65:I$68),2) -> 0 | J69: =ROUND(SUM(J$65:J$68),2) -> 0 | K69: =ROUND(SUM(K$65:K$68),2) -> 0 | L69: =ROUND(SUM(L$65:L$68),2) -> 0 | M69: =ROUND(SUM(M$65:M$68),2) -> 0 | ... AI69: =ROUND(SUM(AI$65:AI$68),2) -> 0
A70: 200cdc67-6a5a-43e0-a8d4-b820eacb321a | B70: 7922b178-da65-4ac7-9731-fd221f980f61 | C70: 1.14.6 | E70: NON CASH ITEMS
A71: fb1d0130-8c1f-414f-9293-03c94a1c0ade | B71: 200cdc67-6a5a-43e0-a8d4-b820eacb321a | C71: 1.14.6.1 | D71: a. | E71: {Others}
A72: 50e3e6b1-ca92-4e82-b2ca-b0b8426846e5 | B72: 200cdc67-6a5a-43e0-a8d4-b820eacb321a | C72: 1.14.6.2 | E72: Sub-total (Non operating income - Non-cash) | F72: =ROUND(SUM(F$71),2) -> 0 | G72: =ROUND(SUM(G$71),2) -> 0 | H72: =ROUND(SUM(H$71),2) -> 0 | I72: =ROUND(SUM(I$71),2) -> 0 | J72: =ROUND(SUM(J$71),2) -> 0 | K72: =ROUND(SUM(K$71),2) -> 0 | L72: =ROUND(SUM(L$71),2) -> 0 | M72: =ROUND(SUM(M$71),2) -> 0 | ... AI72: =ROUND(SUM(AI$71),2) -> 0
A73: 11fa2e28-79b1-4b4e-af42-e071c9bd2d50 | B73: 200cdc67-6a5a-43e0-a8d4-b820eacb321a | C73: 1.14.6.3 | E73: Sub-total (Non operating Income) | F73: =ROUND(F69+F72,2) -> 0 | G73: =ROUND(G69+G72,2) -> 0 | H73: =ROUND(H69+H72,2) -> 0 | I73: =ROUND(I69+I72,2) -> 0 | J73: =ROUND(J69+J72,2) -> 0 | K73: =ROUND(K69+K72,2) -> 0 | L73: =ROUND(L69+L72,2) -> 0 | M73: =ROUND(M69+M72,2) -> 0 | ... AI73: =ROUND(AI69+AI72,2) -> 0
A74: c8016418-d641-48e5-bf69-9b5c6c31110f | B74: 7922b178-da65-4ac7-9731-fd221f980f61 | C74: 1.14.7 | D74: ii. | E74: Deduct: Other non-operating expenses
A75: dd04bf42-b0b2-4c61-8fdd-e65dca71901a | B75: 7922b178-da65-4ac7-9731-fd221f980f61 | C75: 1.14.8 | E75: CASH ITEMS
A76: c84141dc-2e53-4610-a1de-49f74b5bd005 | B76: dd04bf42-b0b2-4c61-8fdd-e65dca71901a | C76: 1.14.8.1 | D76: a. | E76: Crystallized forex loss
A77: 06ee36ea-0c23-4f01-a7d0-a0934ac6fd95 | B77: dd04bf42-b0b2-4c61-8fdd-e65dca71901a | C77: 1.14.8.2 | D77: b. | E77: Write-off of stock-in-process
A78: a839c66b-a310-46bc-a5b7-f502894065cc | B78: dd04bf42-b0b2-4c61-8fdd-e65dca71901a | C78: 1.14.8.3 | D78: c. | E78: Write-off of finished goods
A79: 5b9635ac-d769-4604-8838-145ae69d8c65 | B79: dd04bf42-b0b2-4c61-8fdd-e65dca71901a | C79: 1.14.8.4 | D79: d. | E79: Loss on sale of fixed assets / Investments
A80: 3eb201cc-56e5-4c0f-a24d-1b1b14fda065 | B80: dd04bf42-b0b2-4c61-8fdd-e65dca71901a | C80: 1.14.8.5 | D80: e. | E80: Other non operating cash expenses
A81: d0da1235-e20b-4bca-9be7-8c9237fbf7bc | B81: dd04bf42-b0b2-4c61-8fdd-e65dca71901a | C81: 1.14.8.6 | D81: f | E81: Other non operating cash exp
A82: f9e04cd8-943b-4010-acdb-bc999d78ce72 | B82: dd04bf42-b0b2-4c61-8fdd-e65dca71901a | C82: 1.14.8.7 | E82: Sub-total (Non operating expense -Cash) | F82: =ROUND(SUM(F$76:F$81),2) -> 0 | G82: =ROUND(SUM(G$76:G$81),2) -> 0 | H82: =ROUND(SUM(H$76:H$81),2) -> 0 | I82: =ROUND(SUM(I$76:I$81),2) -> 0 | J82: =ROUND(SUM(J$76:J$81),2) -> 0 | K82: =ROUND(SUM(K$76:K$81),2) -> 0 | L82: =ROUND(SUM(L$76:L$81),2) -> 0 | M82: =ROUND(SUM(M$76:M$81),2) -> 0 | ... AI82: =ROUND(SUM(AI$76:AI$81),2) -> 0
A83: 5d56acf7-0293-4e08-86d3-aaba02132db9 | B83: dd04bf42-b0b2-4c61-8fdd-e65dca71901a | C83: 1.14.8.8 | E83: NON CASH ITEMS
A84: 0f051e4a-a41b-4a99-88c9-feb2365cc72d | B84: 5d56acf7-0293-4e08-86d3-aaba02132db9 | C84: 1.14.8.8.1 | D84: a. | E84: MTM forex loss
A85: d8ec163d-78ac-431c-99e1-8ace8169b883 | B85: 5d56acf7-0293-4e08-86d3-aaba02132db9 | C85: 1.14.8.8.2 | D85: b. | E85: {Others}
A86: 7544d25b-0a55-4517-9df3-cd49a0af62c2 | B86: 5d56acf7-0293-4e08-86d3-aaba02132db9 | C86: 1.14.8.8.3 | E86: Sub-total (Non operating expense - Non-cash) | F86: =ROUND(SUM(F$84:F$85),2) -> 0 | G86: =ROUND(SUM(G$84:G$85),2) -> 0 | H86: =ROUND(SUM(H$84:H$85),2) -> 0 | I86: =ROUND(SUM(I$84:I$85),2) -> 0 | J86: =ROUND(SUM(J$84:J$85),2) -> 0 | K86: =ROUND(SUM(K$84:K$85),2) -> 0 | L86: =ROUND(SUM(L$84:L$85),2) -> 0 | M86: =ROUND(SUM(M$84:M$85),2) -> 0 | ... AI86: =ROUND(SUM(AI$84:AI$85),2) -> 0
A87: 522e2580-1284-415b-8016-2e703f8cee1c | B87: 5d56acf7-0293-4e08-86d3-aaba02132db9 | C87: 1.14.8.8.4 | E87: Sub-total (Non operating expense) | F87: =ROUND(F82+F86,2) -> 0 | G87: =ROUND(G82+G86,2) -> 0 | H87: =ROUND(H82+H86,2) -> 0 | I87: =ROUND(I82+I86,2) -> 0 | J87: =ROUND(J82+J86,2) -> 0 | K87: =ROUND(K82+K86,2) -> 0 | L87: =ROUND(L82+L86,2) -> 0 | M87: =ROUND(M82+M86,2) -> 0 | ... AI87: =ROUND(AI82+AI86,2) -> 0
A88: 84430ae4-7ba5-4ad1-a312-88536b3cc13c | B88: dd04bf42-b0b2-4c61-8fdd-e65dca71901a | C88: 1.14.8.9 | D88: iii | E88: Net of other non-operating income/expenses | F88: =ROUND(F73-F87,2) -> 0 | G88: =ROUND(G73-G87,2) -> 0 | H88: =ROUND(H73-H87,2) -> 0 | I88: =ROUND(I73-I87,2) -> 0 | J88: =ROUND(J73-J87,2) -> 0 | K88: =ROUND(K73-K87,2) -> 0 | L88: =ROUND(L73-L87,2) -> 0 | M88: =ROUND(M73-M87,2) -> 0 | ... AI88: =ROUND(AI73-AI87,2) -> 0
A89: fc317b2b-949e-4375-b1dd-395b77975d15 | B89: c98dd930-c06b-4184-a258-ac39cd19a193 | C89: 1.15 | D89: 12 | E89: Profit before tax/loss [10 + 11(iii)] (PBT) | F89: =ROUND(F62+F88,2) -> 0 | G89: =ROUND(G62+G88,2) -> 0 | H89: =ROUND(H62+H88,2) -> 0 | I89: =ROUND(I62+I88,2) -> 0 | J89: =ROUND(J62+J88,2) -> 0 | K89: =ROUND(K62+K88,2) -> 0 | L89: =ROUND(L62+L88,2) -> 0 | M89: =ROUND(M62+M88,2) -> 0 | ... AI89: =ROUND(AI62+AI88,2) -> 0
A90: bef66092-7c0a-4b22-baf3-56e38869958e | B90: c98dd930-c06b-4184-a258-ac39cd19a193 | C90: 1.16 | D90: 13 | E90: Provision for taxes | F90: =(ROUND(SUM(F$91:F$92),2)) -> 0 | G90: =(ROUND(SUM(G$91:G$92),2)) -> 0 | H90: =(ROUND(SUM(H$91:H$92),2)) -> 0 | I90: =(ROUND(SUM(I$91:I$92),2)) -> 0 | J90: =(ROUND(SUM(J$91:J$92),2)) -> 0 | K90: =(ROUND(SUM(K$91:K$92),2)) -> 0 | L90: =(ROUND(SUM(L$91:L$92),2)) -> 0 | M90: =(ROUND(SUM(M$91:M$92),2)) -> 0 | ... AI90: =(ROUND(SUM(AI$91:AI$92),2)) -> 0
A91: 93833f29-6945-4c8d-af99-31a624848bec | B91: bef66092-7c0a-4b22-baf3-56e38869958e | C91: 1.16.1 | D91: a. | E91: Current tax
A92: ff1fef25-6e87-4bf7-ada2-bca6a29add91 | B92: bef66092-7c0a-4b22-baf3-56e38869958e | C92: 1.16.2 | D92: b. | E92: Deferred tax
A93: 7f24fe60-dfc6-4c6c-b7a4-fed231550438 | B93: c98dd930-c06b-4184-a258-ac39cd19a193 | C93: 1.17 | D93: 14 | E93: Net Profit / Loss (12 -13) (PAT) | F93: =ROUND(F89-F90,2) -> 0 | G93: =ROUND(G89-G90,2) -> 0 | H93: =ROUND(H89-H90,2) -> 0 | I93: =ROUND(I89-I90,2) -> 0 | J93: =ROUND(J89-J90,2) -> 0 | K93: =ROUND(K89-K90,2) -> 0 | L93: =ROUND(L89-L90,2) -> 0 | M93: =ROUND(M89-M90,2) -> 0 | ... AI93: =ROUND(AI89-AI90,2) -> 0
A94: f698f49b-d41b-4833-9daf-e9b2433213db | B94: c98dd930-c06b-4184-a258-ac39cd19a193 | C94: 1.18 | D94: 15 a. | E94: Equity dividend (paid+proposed)
A95: 90548b2b-fa7b-4d84-905a-80961d65a149 | B95: c98dd930-c06b-4184-a258-ac39cd19a193 | C95: 1.19 | D95: b. | E95: Dividend Rate (% age)
A96: 44fbb444-33a1-43f0-83d6-6a66783798d6 | B96: c98dd930-c06b-4184-a258-ac39cd19a193 | C96: 1.20 | D96: 16 | E96: Retained Profit (14 - 15) | F96: =ROUND(F93-F94,2) -> 0 | G96: =ROUND(G93-G94,2) -> 0 | H96: =ROUND(H93-H94,2) -> 0 | I96: =ROUND(I93-I94,2) -> 0 | J96: =ROUND(J93-J94,2) -> 0 | K96: =ROUND(K93-K94,2) -> 0 | L96: =ROUND(L93-L94,2) -> 0 | M96: =ROUND(M93-M94,2) -> 0 | ... AI96: =ROUND(AI93-AI94,2) -> 0
A97: f5b4ddaf-88ee-4c00-95d9-5d29d2f84f13 | B97: c98dd930-c06b-4184-a258-ac39cd19a193 | C97: 1.21 | D97: 17 | E97: Retained Profit / Net Profit (% age) | F97: =IF(F93<>0,(F96/F93),"")*100 -> #VALUE! | G97: =IF(G93<>0,(G96/G93),"")*100 -> #VALUE! | H97: =IF(H93<>0,(H96/H93),"")*100 -> #VALUE! | I97: =IF(I93<>0,(I96/I93),"")*100 -> #VALUE! | J97: =IF(J93<>0,(J96/J93),"")*100 -> #VALUE! | K97: =IF(K93<>0,(K96/K93),"")*100 -> #VALUE! | L97: =IF(L93<>0,(L96/L93),"")*100 -> #VALUE! | M97: =IF(M93<>0,(M96/M93),"")*100 -> #VALUE! | ... AI97: =IF(AI93<>0,(AI96/AI93),"")*100 -> #VALUE!

Sheet Balance Sheet
E1: BORROWER_NAME | F1: =IF('Profit and Loss Statement'!F1="","",'Profit and Loss Statement'!F1)
E2: BORROWER_CODE | F2: =IF('Profit and Loss Statement'!F2="","",'Profit and Loss Statement'!F2)
A3: e99040d4-d820-4ef1-ab86-5cb00d496a30 | E3: TEMPLATE_NAME | F3: Company Financial Template
E4: PROJECT_NAME
E5: ACCOUNTING_TYPE | F5: =IF('Profit and Loss Statement'!F5="","",'Profit and Loss Statement'!F5) -> GAAP | G5: =IF('Profit and Loss Statement'!G5="","",'Profit and Loss Statement'!G5) | H5: =IF('Profit and Loss Statement'!H5="","",'Profit and Loss Statement'!H5) | I5: =IF('Profit and Loss Statement'!I5="","",'Profit and Loss Statement'!I5) | J5: =IF('Profit and Loss Statement'!J5="","",'Profit and Loss Statement'!J5) | K5: =IF('Profit and Loss Statement'!K5="","",'Profit and Loss Statement'!K5) | L5: =IF('Profit and Loss Statement'!L5="","",'Profit and Loss Statement'!L5) | M5: =IF('Profit and Loss Statement'!M5="","",'Profit and Loss Statement'!M5) | ... AI5: =IF('Profit and Loss Statement'!AI5="","",'Profit and Loss Statement'!AI5)
E6: FINANCIAL_TYPE | F6: =IF('Profit and Loss Statement'!F6="","",'Profit and Loss Statement'!F6) -> Consolidated | G6: =IF('Profit and Loss Statement'!G6="","",'Profit and Loss Statement'!G6) | H6: =IF('Profit and Loss Statement'!H6="","",'Profit and Loss Statement'!H6) | I6: =IF('Profit and Loss Statement'!I6="","",'Profit and Loss Statement'!I6) | J6: =IF('Profit and Loss Statement'!J6="","",'Profit and Loss Statement'!J6) | K6: =IF('Profit and Loss Statement'!K6="","",'Profit and Loss Statement'!K6) | L6: =IF('Profit and Loss Statement'!L6="","",'Profit and Loss Statement'!L6) | M6: =IF('Profit and Loss Statement'!M6="","",'Profit and Loss Statement'!M6) | ... AI6: =IF('Profit and Loss Statement'!AI6="","",'Profit and Loss Statement'!AI6)
E7: YEAR | F7: =IF('Profit and Loss Statement'!F7="","",'Profit and Loss Statement'!F7) | G7: =IF('Profit and Loss Statement'!G7="","",'Profit and Loss Statement'!G7) | H7: =IF('Profit and Loss Statement'!H7="","",'Profit and Loss Statement'!H7) | I7: =IF('Profit and Loss Statement'!I7="","",'Profit and Loss Statement'!I7) | J7: =IF('Profit and Loss Statement'!J7="","",'Profit and Loss Statement'!J7) | K7: =IF('Profit and Loss Statement'!K7="","",'Profit and Loss Statement'!K7) | L7: =IF('Profit and Loss Statement'!L7="","",'Profit and Loss Statement'!L7) | M7: =IF('Profit and Loss Statement'!M7="","",'Profit and Loss Statement'!M7) | ... AI7: =IF('Profit and Loss Statement'!AI7="","",'Profit and Loss Statement'!AI7)
E8: YEAR_TYPE | F8: =IF('Profit and Loss Statement'!F8="","",'Profit and Loss Statement'!F8) -> Audited | G8: =IF('Profit and Loss Statement'!G8="","",'Profit and Loss Statement'!G8) | H8: =IF('Profit and Loss Statement'!H8="","",'Profit and Loss Statement'!H8) | I8: =IF('Profit and Loss Statement'!I8="","",'Profit and Loss Statement'!I8) | J8: =IF('Profit and Loss Statement'!J8="","",'Profit and Loss Statement'!J8) | K8: =IF('Profit and Loss Statement'!K8="","",'Profit and Loss Statement'!K8) | L8: =IF('Profit and Loss Statement'!L8="","",'Profit and Loss Statement'!L8) | M8: =IF('Profit and Loss Statement'!M8="","",'Profit and Loss Statement'!M8) | ... AI8: =IF('Profit and Loss Statement'!AI8="","",'Profit and Loss Statement'!AI8)
E9: STATEMENT_DATE (YYYY-MM-DD) | F9: =IF('Profit and Loss Statement'!F9="","",'Profit and Loss Statement'!F9) | G9: =IF('Profit and Loss Statement'!G9="","",'Profit and Loss Statement'!G9) | H9: =IF('Profit and Loss Statement'!H9="","",'Profit and Loss Statement'!H9) | I9: =IF('Profit and Loss Statement'!I9="","",'Profit and Loss Statement'!I9) | J9: =IF('Profit and Loss Statement'!J9="","",'Profit and Loss Statement'!J9) | K9: =IF('Profit and Loss Statement'!K9="","",'Profit and Loss Statement'!K9) | L9: =IF('Profit and Loss Statement'!L9="","",'Profit and Loss Statement'!L9) | M9: =IF('Profit and Loss Statement'!M9="","",'Profit and Loss Statement'!M9) | ... AI9: =IF('Profit and Loss Statement'!AI9="","",'Profit and Loss Statement'!AI9)
E10: NO_OF_MONTHS | F10: =IF('Profit and Loss Statement'!F10="","",'Profit and Loss Statement'!F10) | G10: =IF('Profit and Loss Statement'!G10="","",'Profit and Loss Statement'!G10) | H10: =IF('Profit and Loss Statement'!H10="","",'Profit and Loss Statement'!H10) | I10: =IF('Profit and Loss Statement'!I10="","",'Profit and Loss Statement'!I10) | J10: =IF('Profit and Loss Statement'!J10="","",'Profit and Loss Statement'!J10) | K10: =IF('Profit and Loss Statement'!K10="","",'Profit and Loss Statement'!K10) | L10: =IF('Profit and Loss Statement'!L10="","",'Profit and Loss Statement'!L10) | M10: =IF('Profit and Loss Statement'!M10="","",'Profit and Loss Statement'!M10) | ... AI10: =IF('Profit and Loss Statement'!AI10="","",'Profit and Loss Statement'!AI10)
E11: CURRENCY | F11: =IF('Profit and Loss Statement'!F11="","",'Profit and Loss Statement'!F11) -> INR | G11: =IF('Profit and Loss Statement'!G11="","",'Profit and Loss Statement'!G11) -> INR | H11: =IF('Profit and Loss Statement'!H11="","",'Profit and Loss Statement'!H11) -> INR | I11: =IF('Profit and Loss Statement'!I11="","",'Profit and Loss Statement'!I11) -> INR | J11: =IF('Profit and Loss Statement'!J11="","",'Profit and Loss Statement'!J11) -> INR | K11: =IF('Profit and Loss Statement'!K11="","",'Profit and Loss Statement'!K11) -> INR | L11: =IF('Profit and Loss Statement'!L11="","",'Profit and Loss Statement'!L11) -> INR | M11: =IF('Profit and Loss Statement'!M11="","",'Profit and Loss Statement'!M11) -> INR | ... AI11: =IF('Profit and Loss Statement'!AI11="","",'Profit and Loss Statement'!AI11) -> INR
E12: DENOMINATION | F12: =IF('Profit and Loss Statement'!F12="","",'Profit and Loss Statement'!F12) -> Crores | G12: =IF('Profit and Loss Statement'!G12="","",'Profit and Loss Statement'!G12) -> Crores | H12: =IF('Profit and Loss Statement'!H12="","",'Profit and Loss Statement'!H12) -> Crores | I12: =IF('Profit and Loss Statement'!I12="","",'Profit and Loss Statement'!I12) -> Crores | J12: =IF('Profit and Loss Statement'!J12="","",'Profit and Loss Statement'!J12) -> Crores | K12: =IF('Profit and Loss Statement'!K12="","",'Profit and Loss Statement'!K12) -> Crores | L12: =IF('Profit and Loss Statement'!L12="","",'Profit and Loss Statement'!L12) -> Crores | M12: =IF('Profit and Loss Statement'!M12="","",'Profit and Loss Statement'!M12) -> Crores | ... AI12: =IF('Profit and Loss Statement'!AI12="","",'Profit and Loss Statement'!AI12) -> Crores
E13: AUDITOR_NAME | F13: =IF('Profit and Loss Statement'!F13="","",'Profit and Loss Statement'!F13)
E14: VERSION | F14: =IF('Profit and Loss Statement'!F14="","",'Profit and Loss Statement'!F14)
E15: CIF_ID | F15: =IF('Profit and Loss Statement'!F15="","",'Profit and Loss Statement'!F15)
E16: BASE_YEAR | F16: =IF('Profit and Loss Statement'!F16="","",'Profit and Loss Statement'!F16)
F17: 1 | G17: 2 | H17: 3 | I17: 4 | J17: 5 | K17: 6 | L17: 7 | M17: 8 | N17: 9 | O17: 10 | P17: 11 | Q17: 12 | R17: 13 | S17: 14 | T17: 15 | U17: 16 | V17: 17 | W17: 18 | X17: 19 | Y17: 20 | Z17: 21 | AA17: 22 | AB17: 23 | AC17: 24 | AD17: 25 | AE17: 26 | AF17: 27 | AG17: 28 | AH17: 29 | AI17: 30
A18: UUID | B18: PARENT ID | C18: AUTO_SEQUENCE | D18: INPUT_SEQUENCE | E18: LINE_ITEM_NAME | F18: VALUE | G18: VALUE | H18: VALUE | I18: VALUE | J18: VALUE | K18: VALUE | L18: VALUE | M18: VALUE | N18: VALUE | O18: VALUE | P18: VALUE | Q18: VALUE | R18: VALUE | S18: VALUE | T18: VALUE | U18: VALUE | V18: VALUE | W18: VALUE | X18: VALUE | Y18: VALUE | Z18: VALUE | AA18: VALUE | AB18: VALUE | AC18: VALUE | AD18: VALUE | AE18: VALUE | AF18: VALUE | AG18: VALUE | AH18: VALUE | AI18: VALUE
A19: b2134858-f66e-4654-8e7f-65b9fc91210a | C19: 2 | E19: Balance Sheet
A20: 878de646-becc-492d-a157-3eecec0f591a | B20: b2134858-f66e-4654-8e7f-65b9fc91210a | C20: 2.1 | E20: Balance Sheet (Liabilities)
A21: 06b301db-9d0b-44e9-86a0-a220d1a72804 | B21: 878de646-becc-492d-a157-3eecec0f591a | C21: 2.1.1 | E21: CURRENT LIABILITIES
A22: c6453f22-2f3e-4634-aacb-956d59f1ff9f | B22: 06b301db-9d0b-44e9-86a0-a220d1a72804 | C22: 2.1.1.1 | D22: 1. | E22: Short-term borrowing from banks
A23: eadde075-7734-48ef-9470-b8d214b7937d | B23: c6453f22-2f3e-4634-aacb-956d59f1ff9f | C23: 2.1.1.1.1 | D23: i. | E23: From applicant bank
A24: 0a8ee552-9b62-4de5-a7ca-3826e5d0b2d4 | B24: c6453f22-2f3e-4634-aacb-956d59f1ff9f | C24: 2.1.1.1.2 | D24: ii. | E24: From other banks
A25: afe14fcf-a84e-4d7d-a5cf-7316ce695da4 | B25: c6453f22-2f3e-4634-aacb-956d59f1ff9f | C25: 2.1.1.1.3 | E25: Sub-total [i + ii] (A) | F25: =ROUND(F23+F24,2) -> 0 | G25: =ROUND(G23+G24,2) -> 0 | H25: =ROUND(H23+H24,2) -> 0 | I25: =ROUND(I23+I24,2) -> 0 | J25: =ROUND(J23+J24,2) -> 0 | K25: =ROUND(K23+K24,2) -> 0 | L25: =ROUND(L23+L24,2) -> 0 | M25: =ROUND(M23+M24,2) -> 0 | ... AI25: =ROUND(AI23+AI24,2) -> 0
A26: d6b57745-686a-4ddf-91b2-5c886f8e567a | B26: 06b301db-9d0b-44e9-86a0-a220d1a72804 | C26: 2.1.1.2 | D26: 2.i. | E26: Short term borrowings from others (including mobilization advance)
A27: f9680623-61e8-4e11-9328-3655ee3c1840 | B27: 06b301db-9d0b-44e9-86a0-a220d1a72804 | C27: 2.1.1.3 | D27: ii. | E27: Short term borrowings from Related Parties
A28: 2a445707-4b7f-4173-83b0-14a8e82e561d | B28: 06b301db-9d0b-44e9-86a0-a220d1a72804 | C28: 2.1.1.4 | D28: 3 | E28: Sundry Creditors (Trade)
A29: 801bc503-eff2-4fcd-af1f-8fbd888c91e3 | B29: 06b301db-9d0b-44e9-86a0-a220d1a72804 | C29: 2.1.1.5 | D29: 4 | E29: Advance payments from customers
A30: a2fd7c99-e51a-4e8a-9619-ffea2ed95393 | B30: 06b301db-9d0b-44e9-86a0-a220d1a72804 | C30: 2.1.1.6 | D30: 5 | E30: Provision for taxation
A31: 49b4e462-3a69-4beb-bdd4-49d9f68a147d | B31: 06b301db-9d0b-44e9-86a0-a220d1a72804 | C31: 2.1.1.7 | D31: 6 | E31: Dividend payable
A32: f1ed247e-11bf-41ae-898d-fee1afa02fdb | B32: 06b301db-9d0b-44e9-86a0-a220d1a72804 | C32: 2.1.1.8 | D32: 7 | E32: Other statutory liabilities (due within 1 year)
A33: d70aad0f-962f-4965-a439-72a29570179e | B33: 06b301db-9d0b-44e9-86a0-a220d1a72804 | C33: 2.1.1.9 | D33: 8 | E33: Installments of liabilities due within one year (CPLTD) | F33: =SUM(F$34:F$38) -> 0 | G33: =SUM(G$34:G$38) -> 0 | H33: =SUM(H$34:H$38) -> 0 | I33: =SUM(I$34:I$38) -> 0 | J33: =SUM(J$34:J$38) -> 0 | K33: =SUM(K$34:K$38) -> 0 | L33: =SUM(L$34:L$38) -> 0 | M33: =SUM(M$34:M$38) -> 0 | ... AI33: =SUM(AI$34:AI$38) -> 0
A34: 1398600f-6534-4439-b9f8-62e09e9e4a9b | B34: d70aad0f-962f-4965-a439-72a29570179e | C34: 2.1.1.9.1 | D34: a. | E34: Debentures
A35: c35f7b5e-c85c-4790-8e55-59328184ae50 | B35: d70aad0f-962f-4965-a439-72a29570179e | C35: 2.1.1.9.2 | D35: b. | E35: Preference Shares
A36: b2e9612d-5c39-44fb-866b-a18539f01e4c | B36: d70aad0f-962f-4965-a439-72a29570179e | C36: 2.1.1.9.3 | D36: c. | E36: Rupee Term loans
A37: 92dcf598-a513-414f-ad4f-174cf6291232 | B37: d70aad0f-962f-4965-a439-72a29570179e | C37: 2.1.1.9.4 | D37: d. | E37: Foreign currency loans
A38: aeb0b18d-923d-43c3-a5c8-4477844c9658 | B38: d70aad0f-962f-4965-a439-72a29570179e | C38: 2.1.1.9.5 | D38: e. | E38: Others
A39: ee760a95-6a92-4837-8442-b1904df695f9 | B39: 06b301db-9d0b-44e9-86a0-a220d1a72804 | C39: 2.1.1.10 | D39: 9 | E39: Other current liabilities & provisions | F39: =ROUND(SUM(F$40:F$45),2) -> 0 | G39: =ROUND(SUM(G$40:G$45),2) -> 0 | H39: =ROUND(SUM(H$40:H$45),2) -> 0 | I39: =ROUND(SUM(I$40:I$45),2) -> 0 | J39: =ROUND(SUM(J$40:J$45),2) -> 0 | K39: =ROUND(SUM(K$40:K$45),2) -> 0 | L39: =ROUND(SUM(L$40:L$45),2) -> 0 | M39: =ROUND(SUM(M$40:M$45),2) -> 0 | ... AI39: =ROUND(SUM(AI$40:AI$45),2) -> 0
A40: 99352122-0c01-4f7f-b9bc-4a04097c3cac | B40: ee760a95-6a92-4837-8442-b1904df695f9 | C40: 2.1.1.10.1 | D40: a. | E40: Creditors for Expenses
A41: 49ed1679-76b5-463a-b8d3-92917e4f8108 | B41: ee760a95-6a92-4837-8442-b1904df695f9 | C41: 2.1.1.10.2 | D41: b. | E41: Employee expenses payable
A42: df71b880-a8db-48ae-9fa8-f3eae49c2004 | B42: ee760a95-6a92-4837-8442-b1904df695f9 | C42: 2.1.1.10.3 | D42: c. | E42: MTM forex loss
A43: 877f41bf-f2cc-4f28-a609-73c32a4f633a | B43: ee760a95-6a92-4837-8442-b1904df695f9 | C43: 2.1.1.10.4 | D43: d. | E43: Interest accrued
A44: f408af15-73c5-4b4d-853a-4f20291f0acc | B44: ee760a95-6a92-4837-8442-b1904df695f9 | C44: 2.1.1.10.5 | D44: e. | E44: Outstanding lease rentals
A45: 6ecc6080-c565-4796-9c90-fdeb3bf71a8f | B45: ee760a95-6a92-4837-8442-b1904df695f9 | C45: 2.1.1.10.6 | D45: f. | E45: {Others}
A46: c60b8f28-78db-4086-b2ca-938725d06a33 | B46: ee760a95-6a92-4837-8442-b1904df695f9 | C46: 2.1.1.10.7 | E46: Sub total [2 to 9] (B) | F46: =SUM(F$26:F$33)+F39 -> 0 | G46: =SUM(G$26:G$33)+G39 -> 0 | H46: =SUM(H$26:H$33)+H39 -> 0 | I46: =SUM(I$26:I$33)+I39 -> 0 | J46: =SUM(J$26:J$33)+J39 -> 0 | K46: =SUM(K$26:K$33)+K39 -> 0 | L46: =SUM(L$26:L$33)+L39 -> 0 | M46: =SUM(M$26:M$33)+M39 -> 0 | ... AI46: =SUM(AI$26:AI$33)+AI39 -> 0
A47: 650b7e27-abed-4d8f-a70c-eef1966ff376 | B47: 06b301db-9d0b-44e9-86a0-a220d1a72804 | C47: 2.1.1.11 | D47: 10 | E47: Total current liabilities [A + B] | F47: =ROUND(F25+F46,2) -> 0 | G47: =ROUND(G25+G46,2) -> 0 | H47: =ROUND(H25+H46,2) -> 0 | I47: =ROUND(I25+I46,2) -> 0 | J47: =ROUND(J25+J46,2) -> 0 | K47: =ROUND(K25+K46,2) -> 0 | L47: =ROUND(L25+L46,2) -> 0 | M47: =ROUND(M25+M46,2) -> 0 | ... AI47: =ROUND(AI25+AI46,2) -> 0
A48: 56fe2b39-9f25-429e-aa60-a18d6efa1174 | B48: 06b301db-9d0b-44e9-86a0-a220d1a72804 | C48: 2.1.1.12
A49: 18997252-f0d1-4925-9c12-e8c690e9bf4e | B49: 878de646-becc-492d-a157-3eecec0f591a | C49: 2.1.2 | E49: TERM LIABILITIES
A50: d7725e28-c20f-476b-a80b-e78e63fdcd52 | B50: 18997252-f0d1-4925-9c12-e8c690e9bf4e | C50: 2.1.2.1 | D50: 11 | E50: Debentures & Preference Shares (not maturing within 1 year)
A51: 40d5ae42-ab48-4303-8f63-50d25dc98d44 | B51: 18997252-f0d1-4925-9c12-e8c690e9bf4e | C51: 2.1.2.2 | D51: 12 | E51: Lease Liabilities
A52: 722d0a4b-7cfa-4889-a658-918bd5348e4e | B52: 18997252-f0d1-4925-9c12-e8c690e9bf4e | C52: 2.1.2.3 | D52: 13.i. | E52: Rupee Term loans (excl. instalments payable within 1 year)
A53: 9eded9ed-f0dd-4ae8-8f1c-8af88a5c8b59 | B53: 18997252-f0d1-4925-9c12-e8c690e9bf4e | C53: 2.1.2.4 | D53: 13.ii | E53: Foreign currency loans (excl. instalments payable within 1 year)
A54: 9105cbfa-e900-44a9-8825-82014db3ea4c | B54: 18997252-f0d1-4925-9c12-e8c690e9bf4e | C54: 2.1.2.5 | D54: 14 | E54: Term deposits including mobilization advance (repayable after 1 year)
A55: 4e0027be-38fb-4dd8-af3c-d3e7aaeeba99 | B55: 18997252-f0d1-4925-9c12-e8c690e9bf4e | C55: 2.1.2.6 | D55: 15 | E55: Long term borrowings from Related parties
A56: bc776d8e-800d-4b8a-a3ea-f05ac797a2e8 | B56: 18997252-f0d1-4925-9c12-e8c690e9bf4e | C56: 2.1.2.7 | D56: 16 | E56: Other term liabilities not considered as debt (incl. Deferred tax liabilities)
A57: 992d4dab-95f4-4994-b5d0-eb8b257947ee | B57: 18997252-f0d1-4925-9c12-e8c690e9bf4e | C57: 2.1.2.8 | D57: 17 | E57: Total Term Liabilities [11 to 16] | F57: =ROUND(SUM(F50:F56),2) -> 0 | G57: =ROUND(SUM(G50:G56),2) -> 0 | H57: =ROUND(SUM(H50:H56),2) -> 0 | I57: =ROUND(SUM(I50:I56),2) -> 0 | J57: =ROUND(SUM(J50:J56),2) -> 0 | K57: =ROUND(SUM(K50:K56),2) -> 0 | L57: =ROUND(SUM(L50:L56),2) -> 0 | M57: =ROUND(SUM(M50:M56),2) -> 0 | ... AI57: =ROUND(SUM(AI50:AI56),2) -> 0
A58: 03b015fb-f7e8-4e3d-9b6c-8aa4c9410dde | B58: 18997252-f0d1-4925-9c12-e8c690e9bf4e | C58: 2.1.2.9 | D58: 18 | E58: Total Outside Liabilities [10 + 17] | F58: =ROUND(F47+F57,2) -> 0 | G58: =ROUND(G47+G57,2) -> 0 | H58: =ROUND(H47+H57,2) -> 0 | I58: =ROUND(I47+I57,2) -> 0 | J58: =ROUND(J47+J57,2) -> 0 | K58: =ROUND(K47+K57,2) -> 0 | L58: =ROUND(L47+L57,2) -> 0 | M58: =ROUND(M47+M57,2) -> 0 | ... AI58: =ROUND(AI47+AI57,2) -> 0
A59: 8f301c0e-160d-4fb6-bc47-c6b69e4a02ec | B59: 18997252-f0d1-4925-9c12-e8c690e9bf4e | C59: 2.1.2.10
A60: 39c8ce25-6ead-479f-9974-cf2971ca9e3b | B60: 878de646-becc-492d-a157-3eecec0f591a | C60: 2.1.3 | E60: NET WORTH
A61: 48ffc5a7-936d-4c88-9cb9-c8d17f8351c4 | B61: 39c8ce25-6ead-479f-9974-cf2971ca9e3b | C61: 2.1.3.1 | D61: 19 | E61: Ordinary Share Capital
A62: 01988d44-db38-444c-8363-c5b4882d5466 | B62: 39c8ce25-6ead-479f-9974-cf2971ca9e3b | C62: 2.1.3.2 | D62: 20 | E62: General Reserve
A63: 517da130-76ad-45ca-8694-b075b02b69fc | B63: 39c8ce25-6ead-479f-9974-cf2971ca9e3b | C63: 2.1.3.3 | D63: 21 | E63: Revaluation Reserve
A64: 50ad6c75-2d36-4e69-ae9a-fe8ff48952e6 | B64: 39c8ce25-6ead-479f-9974-cf2971ca9e3b | C64: 2.1.3.4 | D64: 22 | E64: Other Reserves (excluding Provisions)
A65: 182bfeef-b204-4747-9d62-352522f0eb38 | B65: 39c8ce25-6ead-479f-9974-cf2971ca9e3b | C65: 2.1.3.5 | D65: 23 | E65: Surplus (+) or deficit (-) in Profit & Loss a/c | G65: =F65+'Profit and Loss Statement'!G96 -> 0 | H65: =G65+'Profit and Loss Statement'!H96 -> 0 | I65: =H65+'Profit and Loss Statement'!I96 -> 0 | J65: =I65+'Profit and Loss Statement'!J96 -> 0 | K65: =J65+'Profit and Loss Statement'!K96 -> 0 | L65: =K65+'Profit and Loss Statement'!L96 -> 0 | M65: =L65+'Profit and Loss Statement'!M96 -> 0 | N65: =M65+'Profit and Loss Statement'!N96 -> 0 | ... AI65: =AH65+'Profit and Loss Statement'!AI96 -> 0
A66: 240b321c-df8d-4490-a9b5-ef2aae0dceac | B66: 39c8ce25-6ead-479f-9974-cf2971ca9e3b | C66: 2.1.3.6 | D66: 24 | E66: Others
A67: e4683308-35d0-4d1c-92f8-1f92dbf24e05 | B67: 240b321c-df8d-4490-a9b5-ef2aae0dceac | C67: 2.1.3.6.1 | D67: a. | E67: Share Premium
A68: e249325d-e9eb-4bad-8ceb-28910c7479d3 | B68: 240b321c-df8d-4490-a9b5-ef2aae0dceac | C68: 2.1.3.6.2 | D68: b. | E68: Capital Redemption Reserve
A69: 404bbab2-9a65-4399-a7d9-7cbe58451060 | B69: 240b321c-df8d-4490-a9b5-ef2aae0dceac | C69: 2.1.3.6.3 | D69: c. | E69: Share application money
A70: 8df8dcd7-4743-4a01-bb22-cd27b1e9add7 | B70: 240b321c-df8d-4490-a9b5-ef2aae0dceac | C70: 2.1.3.6.4 | D70: d. | E70: Foreign currency translation reserve
A71: 89a69505-99e1-4804-972f-5b7fc342a226 | B71: 240b321c-df8d-4490-a9b5-ef2aae0dceac | C71: 2.1.3.6.5 | D71: e. | E71: Minority Interest
A72: f16411d8-6403-4e01-ad0e-63a4c1b1cafb | B72: 240b321c-df8d-4490-a9b5-ef2aae0dceac | C72: 2.1.3.6.6 | D72: f. | E72: Quasi Equity
A73: bf6932bf-76c2-4ab6-87b5-29909e7cbe34 | B73: 240b321c-df8d-4490-a9b5-ef2aae0dceac | C73: 2.1.3.6.7 | D73: g. | E73: Others
A74: a590a497-04de-4fc5-887b-3d226a136654 | B74: 39c8ce25-6ead-479f-9974-cf2971ca9e3b | C74: 2.1.3.7 | D74: 25 | E74: NET WORTH | F74: =SUM(F61:F73) -> 0 | G74: =SUM(G61:G73) -> 0 | H74: =SUM(H61:H73) -> 0 | I74: =SUM(I61:I73) -> 0 | J74: =SUM(J61:J73) -> 0 | K74: =SUM(K61:K73) -> 0 | L74: =SUM(L61:L73) -> 0 | M74: =SUM(M61:M73) -> 0 | ... AI74: =SUM(AI61:AI73) -> 0
A75: 045ee751-40cd-4566-b7e7-e823de4b675d | B75: 39c8ce25-6ead-479f-9974-cf2971ca9e3b | C75: 2.1.3.8 | D75: 26 | E75: TOTAL LIABILITIES [18 + 24] | F75: =ROUND(F58+F74,2) -> 0 | G75: =ROUND(G58+G74,2) -> 0 | H75: =ROUND(H58+H74,2) -> 0 | I75: =ROUND(I58+I74,2) -> 0 | J75: =ROUND(J58+J74,2) -> 0 | K75: =ROUND(K58+K74,2) -> 0 | L75: =ROUND(L58+L74,2) -> 0 | M75: =ROUND(M58+M74,2) -> 0 | ... AI75: =ROUND(AI58+AI74,2) -> 0
A76: 691019ab-e7af-4888-bf3e-e40adc9b38dd | B76: b2134858-f66e-4654-8e7f-65b9fc91210a | C76: 2.2
A77: ccaeeff2-0c88-4a79-94ba-c773d127e08b | B77: b2134858-f66e-4654-8e7f-65b9fc91210a | C77: 2.3 | E77: Balance Sheet (Assets)
A78: 4ca0e56d-2fe6-483a-96c1-8a4951874ccb | B78: ccaeeff2-0c88-4a79-94ba-c773d127e08b | C78: 2.3.1 | E78: CURRENT ASSETS
A79: 9d1a08ef-e967-4814-87a0-938bd3b5b6cd | B79: 4ca0e56d-2fe6-483a-96c1-8a4951874ccb | C79: 2.3.1.1 | D79: 27 | E79: Cash and Bank Balances | F79: =F80+F81 -> 0 | G79: =G80+G81 -> 0 | H79: =H80+H81 -> 0 | I79: =I80+I81 -> 0 | J79: =J80+J81 -> 0 | K79: =K80+K81 -> 0 | L79: =L80+L81 -> 0 | M79: =M80+M81 -> 0 | ... AI79: =AI80+AI81 -> 0
A80: 2fc39a34-6347-40a6-ac0a-945e629e7d63 | B80: 9d1a08ef-e967-4814-87a0-938bd3b5b6cd | C80: 2.3.1.1.1 | D80: i. | E80: Cash balance
A81: da98dfc4-2e15-433e-8f95-e9dc80fe0c6b | B81: 9d1a08ef-e967-4814-87a0-938bd3b5b6cd | C81: 2.3.1.1.2 | D81: ii. | E81: Bank balance
A82: 7e59a039-4732-4a16-b96a-3cb340f2730c | B82: 4ca0e56d-2fe6-483a-96c1-8a4951874ccb | C82: 2.3.1.2 | D82: 28 | E82: Investments (other than long term)
A83: 4e23f959-1091-4697-a2fa-8ac79e1bb81d | B83: 7e59a039-4732-4a16-b96a-3cb340f2730c | C83: 2.3.1.2.1 | D83: i. | E83: Govt. and other trustee securities
A84: cf7c44c0-3022-4651-ac01-f305fa06ad15 | B84: 7e59a039-4732-4a16-b96a-3cb340f2730c | C84: 2.3.1.2.2 | D84: ii. | E84: Fixed Deposits with banks
A85: d2dc36c7-db7b-43da-bc14-b65431da7071 | B85: 4ca0e56d-2fe6-483a-96c1-8a4951874ccb | C85: 2.3.1.3 | D85: 29 | E85: Receivables (incldg. bills purchased and discounted by banks) | F85: =F86+F87 -> 0 | G85: =G86+G87 -> 0 | H85: =H86+H87 -> 0 | I85: =I86+I87 -> 0 | J85: =J86+J87 -> 0 | K85: =K86+K87 -> 0 | L85: =L86+L87 -> 0 | M85: =M86+M87 -> 0 | ... AI85: =AI86+AI87 -> 0
A86: 3ae8584a-68c1-477b-8f26-59cab14ad83b | B86: d2dc36c7-db7b-43da-bc14-b65431da7071 | C86: 2.3.1.3.1 | D86: 1. | E86: Domestic Receivables
A87: be0dee3a-96a0-4b5d-932f-ffcc17b58613 | B87: d2dc36c7-db7b-43da-bc14-b65431da7071 | C87: 2.3.1.3.2 | D87: ii. | E87: Export Receivables
A88: 22bb2195-0b98-482e-bee3-b0e55f095ccb | B88: 4ca0e56d-2fe6-483a-96c1-8a4951874ccb | C88: 2.3.1.4 | D88: 30 | E88: Instalments of deferred receivables (due within 1 year)
A89: c651484d-b6f4-4ae1-8ca5-503cb0a657bc | B89: 4ca0e56d-2fe6-483a-96c1-8a4951874ccb | C89: 2.3.1.5 | D89: 31 | E89: Inventory: | F89: =ROUND(F91+F92+F93+F94+F95,2) -> 0 | G89: =ROUND(G91+G92+G93+G94+G95,2) -> 0 | H89: =ROUND(H91+H92+H93+H94+H95,2) -> 0 | I89: =ROUND(I91+I92+I93+I94+I95,2) -> 0 | J89: =ROUND(J91+J92+J93+J94+J95,2) -> 0 | K89: =ROUND(K91+K92+K93+K94+K95,2) -> 0 | L89: =ROUND(L91+L92+L93+L94+L95,2) -> 0 | M89: =ROUND(M91+M92+M93+M94+M95,2) -> 0 | ... AI89: =ROUND(AI91+AI92+AI93+AI94+AI95,2) -> 0
A90: d4babf8a-08ab-4d2c-88d6-02fa6a052534 | B90: c651484d-b6f4-4ae1-8ca5-503cb0a657bc | C90: 2.3.1.5.1 | D90: i. | E90: Raw materials | F90: =ROUND(SUM(F91:F92),2) -> 0 | G90: =ROUND(SUM(G91:G92),2) -> 0 | H90: =ROUND(SUM(H91:H92),2) -> 0 | I90: =ROUND(SUM(I91:I92),2) -> 0 | J90: =ROUND(SUM(J91:J92),2) -> 0 | K90: =ROUND(SUM(K91:K92),2) -> 0 | L90: =ROUND(SUM(L91:L92),2) -> 0 | M90: =ROUND(SUM(M91:M92),2) -> 0 | ... AI90: =ROUND(SUM(AI91:AI92),2) -> 0
A91: 4ecd7297-336d-441b-8f94-98d45accb6bd | B91: d4babf8a-08ab-4d2c-88d6-02fa6a052534 | C91: 2.3.1.5.1.1 | D91: a. | E91: Imported
A92: c24ac2ab-cff2-4c54-9629-0eaf62632678 | B92: d4babf8a-08ab-4d2c-88d6-02fa6a052534 | C92: 2.3.1.5.1.2 | D92: b. | E92: Indigenous
A93: 3d05c545-b582-47d0-ad4a-624704ec6e89 | B93: c651484d-b6f4-4ae1-8ca5-503cb0a657bc | C93: 2.3.1.5.2 | D93: ii. | E93: Stocks-in-process
A94: b242879b-71fd-4e31-b91c-4f4745a320b5 | B94: c651484d-b6f4-4ae1-8ca5-503cb0a657bc | C94: 2.3.1.5.3 | D94: iii. | E94: Finished goods
A95: 72a063be-d21c-4574-8e1e-3b6f85c6f4a7 | B95: c651484d-b6f4-4ae1-8ca5-503cb0a657bc | C95: 2.3.1.5.4 | D95: iv. | E95: Other consumable spares
A96: 5c62c4b3-57f4-4cd1-bb71-22f98201c595 | B96: 4ca0e56d-2fe6-483a-96c1-8a4951874ccb | C96: 2.3.1.6 | D96: 32 | E96: Advances to suppliers of raw materials, stores and spares
A97: c39e1a66-df9a-4c16-8b8d-d721d1913b99 | B97: 4ca0e56d-2fe6-483a-96c1-8a4951874ccb | C97: 2.3.1.7 | D97: 33 | E97: Advance payment of taxes
A98: 9074a3d5-ccee-4858-bb56-2d32c681ee08 | B98: 4ca0e56d-2fe6-483a-96c1-8a4951874ccb | C98: 2.3.1.8 | D98: 34 | E98: Other current assets (specify major items) | F98: =ROUND(SUM(F$99:F$103),2) -> 0 | G98: =ROUND(SUM(G$99:G$103),2) -> 0 | H98: =ROUND(SUM(H$99:H$103),2) -> 0 | I98: =ROUND(SUM(I$99:I$103),2) -> 0 | J98: =ROUND(SUM(J$99:J$103),2) -> 0 | K98: =ROUND(SUM(K$99:K$103),2) -> 0 | L98: =ROUND(SUM(L$99:L$103),2) -> 0 | M98: =ROUND(SUM(M$99:M$103),2) -> 0 | ... AI98: =ROUND(SUM(AI$99:AI$103),2) -> 0
A99: dd86161a-5364-41b6-8869-f8ca48617dd4 | B99: 9074a3d5-ccee-4858-bb56-2d32c681ee08 | C99: 2.3.1.8.1 | D99: a. | E99: Interest Receivable
A100: 453dec9c-30f0-48dd-abba-9994786209e9 | B100: 9074a3d5-ccee-4858-bb56-2d32c681ee08 | C100: 2.3.1.8.2 | D100: b. | E100: Prepaid Expenses
...

Sheet Additional Information
E1: BORROWER_NAME | F1: =IF('Profit and Loss Statement'!F1="","",'Profit and Loss Statement'!F1)
E2: BORROWER_CODE | F2: =IF('Profit and Loss Statement'!F2="","",'Profit and Loss Statement'!F2)
A3: 4ac3c202-727e-4341-8d5b-85a2bfaa5a5a | E3: TEMPLATE_NAME | F3: Company Financial Template
E4: PROJECT_NAME | F4: =IF('Profit and Loss Statement'!F4="","",'Profit and Loss Statement'!F4)
E5: ACCOUNTING_TYPE | F5: =IF('Profit and Loss Statement'!F5="","",'Profit and Loss Statement'!F5) -> GAAP | G5: =IF('Profit and Loss Statement'!G5="","",'Profit and Loss Statement'!G5) | H5: =IF('Profit and Loss Statement'!H5="","",'Profit and Loss Statement'!H5) | I5: =IF('Profit and Loss Statement'!I5="","",'Profit and Loss Statement'!I5) | J5: =IF('Profit and Loss Statement'!J5="","",'Profit and Loss Statement'!J5) | K5: =IF('Profit and Loss Statement'!K5="","",'Profit and Loss Statement'!K5) | L5: =IF('Profit and Loss Statement'!L5="","",'Profit and Loss Statement'!L5) | M5: =IF('Profit and Loss Statement'!M5="","",'Profit and Loss Statement'!M5) | ... AI5: =IF('Profit and Loss Statement'!AI5="","",'Profit and Loss Statement'!AI5)
E6: FINANCIAL_TYPE | F6: =IF('Profit and Loss Statement'!F6="","",'Profit and Loss Statement'!F6) -> Consolidated | G6: =IF('Profit and Loss Statement'!G6="","",'Profit and Loss Statement'!G6) | H6: =IF('Profit and Loss Statement'!H6="","",'Profit and Loss Statement'!H6) | I6: =IF('Profit and Loss Statement'!I6="","",'Profit and Loss Statement'!I6) | J6: =IF('Profit and Loss Statement'!J6="","",'Profit and Loss Statement'!J6) | K6: =IF('Profit and Loss Statement'!K6="","",'Profit and Loss Statement'!K6) | L6: =IF('Profit and Loss Statement'!L6="","",'Profit and Loss Statement'!L6) | M6: =IF('Profit and Loss Statement'!M6="","",'Profit and Loss Statement'!M6) | ... AI6: =IF('Profit and Loss Statement'!AI6="","",'Profit and Loss Statement'!AI6)
E7: YEAR | F7: =IF('Profit and Loss Statement'!F7="","",'Profit and Loss Statement'!F7) | G7: =IF('Profit and Loss Statement'!G7="","",'Profit and Loss Statement'!G7) | H7: =IF('Profit and Loss Statement'!H7="","",'Profit and Loss Statement'!H7) | I7: =IF('Profit and Loss Statement'!I7="","",'Profit and Loss Statement'!I7) | J7: =IF('Profit and Loss Statement'!J7="","",'Profit and Loss Statement'!J7) | K7: =IF('Profit and Loss Statement'!K7="","",'Profit and Loss Statement'!K7) | L7: =IF('Profit and Loss Statement'!L7="","",'Profit and Loss Statement'!L7) | M7: =IF('Profit and Loss Statement'!M7="","",'Profit and Loss Statement'!M7) | ... AI7: =IF('Profit and Loss Statement'!AI7="","",'Profit and Loss Statement'!AI7)
E8: YEAR_TYPE | F8: =IF('Profit and Loss Statement'!F8="","",'Profit and Loss Statement'!F8) -> Audited | G8: =IF('Profit and Loss Statement'!G8="","",'Profit and Loss Statement'!G8) | H8: =IF('Profit and Loss Statement'!H8="","",'Profit and Loss Statement'!H8) | I8: =IF('Profit and Loss Statement'!I8="","",'Profit and Loss Statement'!I8) | J8: =IF('Profit and Loss Statement'!J8="","",'Profit and Loss Statement'!J8) | K8: =IF('Profit and Loss Statement'!K8="","",'Profit and Loss Statement'!K8) | L8: =IF('Profit and Loss Statement'!L8="","",'Profit and Loss Statement'!L8) | M8: =IF('Profit and Loss Statement'!M8="","",'Profit and Loss Statement'!M8) | ... AI8: =IF('Profit and Loss Statement'!AI8="","",'Profit and Loss Statement'!AI8)
E9: STATEMENT_DATE (YYYY-MM-DD) | F9: =IF('Profit and Loss Statement'!F9="","",'Profit and Loss Statement'!F9) | G9: =IF('Profit and Loss Statement'!G9="","",'Profit and Loss Statement'!G9) | H9: =IF('Profit and Loss Statement'!H9="","",'Profit and Loss Statement'!H9) | I9: =IF('Profit and Loss Statement'!I9="","",'Profit and Loss Statement'!I9) | J9: =IF('Profit and Loss Statement'!J9="","",'Profit and Loss Statement'!J9) | K9: =IF('Profit and Loss Statement'!K9="","",'Profit and Loss Statement'!K9) | L9: =IF('Profit and Loss Statement'!L9="","",'Profit and Loss Statement'!L9) | M9: =IF('Profit and Loss Statement'!M9="","",'Profit and Loss Statement'!M9) | ... AI9: =IF('Profit and Loss Statement'!AI9="","",'Profit and Loss Statement'!AI9)
E10: NO_OF_MONTHS | F10: =IF('Profit and Loss Statement'!F10="","",'Profit and Loss Statement'!F10) | G10: =IF('Profit and Loss Statement'!G10="","",'Profit and Loss Statement'!G10) | H10: =IF('Profit and Loss Statement'!H10="","",'Profit and Loss Statement'!H10) | I10: =IF('Profit and Loss Statement'!I10="","",'Profit and Loss Statement'!I10) | J10: =IF('Profit and Loss Statement'!J10="","",'Profit and Loss Statement'!J10) | K10: =IF('Profit and Loss Statement'!K10="","",'Profit and Loss Statement'!K10) | L10: =IF('Profit and Loss Statement'!L10="","",'Profit and Loss Statement'!L10) | M10: =IF('Profit and Loss Statement'!M10="","",'Profit and Loss Statement'!M10) | ... AI10: =IF('Profit and Loss Statement'!AI10="","",'Profit and Loss Statement'!AI10)
E11: CURRENCY | F11: =IF('Profit and Loss Statement'!F11="","",'Profit and Loss Statement'!F11) -> INR | G11: =IF('Profit and Loss Statement'!G11="","",'Profit and Loss Statement'!G11) -> INR | H11: =IF('Profit and Loss Statement'!H11="","",'Profit and Loss Statement'!H11) -> INR | I11: =IF('Profit and Loss Statement'!I11="","",'Profit and Loss Statement'!I11) -> INR | J11: =IF('Profit and Loss Statement'!J11="","",'Profit and Loss Statement'!J11) -> INR | K11: =IF('Profit and Loss Statement'!K11="","",'Profit and Loss Statement'!K11) -> INR | L11: =IF('Profit and Loss Statement'!L11="","",'Profit and Loss Statement'!L11) -> INR | M11: =IF('Profit and Loss Statement'!M11="","",'Profit and Loss Statement'!M11) -> INR | ... AI11: =IF('Profit and Loss Statement'!AI11="","",'Profit and Loss Statement'!AI11) -> INR
E12: DENOMINATION | F12: =IF('Profit and Loss Statement'!F12="","",'Profit and Loss Statement'!F12) -> Crores | G12: =IF('Profit and Loss Statement'!G12="","",'Profit and Loss Statement'!G12) -> Crores | H12: =IF('Profit and Loss Statement'!H12="","",'Profit and Loss Statement'!H12) -> Crores | I12: =IF('Profit and Loss Statement'!I12="","",'Profit and Loss Statement'!I12) -> Crores | J12: =IF('Profit and Loss Statement'!J12="","",'Profit and Loss Statement'!J12) -> Crores | K12: =IF('Profit and Loss Statement'!K12="","",'Profit and Loss Statement'!K12) -> Crores | L12: =IF('Profit and Loss Statement'!L12="","",'Profit and Loss Statement'!L12) -> Crores | M12: =IF('Profit and Loss Statement'!M12="","",'Profit and Loss Statement'!M12) -> Crores | ... AI12: =IF('Profit and Loss Statement'!AI12="","",'Profit and Loss Statement'!AI12) -> Crores
E13: AUDITOR_NAME | F13: =IF('Profit and Loss Statement'!F13="","",'Profit and Loss Statement'!F13)
E14: VERSION | F14: =IF('Profit and Loss Statement'!F14="","",'Profit and Loss Statement'!F14)
E15: CIF_ID | F15: =IF('Profit and Loss Statement'!F15="","",'Profit and Loss Statement'!F15)
E16: BASE_YEAR | F16: =IF('Profit and Loss Statement'!F16="","",'Profit and Loss Statement'!F16)
F17: 1 | G17: 2 | H17: 3 | I17: 4 | J17: 5 | K17: 6 | L17: 7 | M17: 8 | N17: 9 | O17: 10 | P17: 11 | Q17: 12 | R17: 13 | S17: 14 | T17: 15 | U17: 16 | V17: 17 | W17: 18 | X17: 19 | Y17: 20 | Z17: 21 | AA17: 22 | AB17: 23 | AC17: 24 | AD17: 25 | AE17: 26 | AF17: 27 | AG17: 28 | AH17: 29 | AI17: 30
A18: UUID | B18: PARENT ID | C18: AUTO_SEQUENCE | D18: INPUT_SEQUENCE | E18: LINE_ITEM_NAME | F18: VALUE | G18: VALUE | H18: VALUE | I18: VALUE | J18: VALUE | K18: VALUE | L18: VALUE | M18: VALUE | N18: VALUE | O18: VALUE | P18: VALUE | Q18: VALUE | R18: VALUE | S18: VALUE | T18: VALUE | U18: VALUE | V18: VALUE | W18: VALUE | X18: VALUE | Y18: VALUE | Z18: VALUE | AA18: VALUE | AB18: VALUE | AC18: VALUE | AD18: VALUE | AE18: VALUE | AF18: VALUE | AG18: VALUE | AH18: VALUE | AI18: VALUE
A19: 0dba63d6-0776-413f-8351-2f2222c3cb3f | C19: 3 | E19: Additional Information
A20: b819a9c0-df6d-41e8-a77f-2e13875e4712 | B20: 0dba63d6-0776-413f-8351-2f2222c3cb3f | C20: 3.1 | D20: A. | E20: Contingent Liabilities: | F20: =SUM(F21:F30) -> 0 | G20: =SUM(G21:G30) -> 0 | H20: =SUM(H21:H30) -> 0 | I20: =SUM(I21:I30) -> 0 | J20: =SUM(J21:J30) -> 0 | K20: =SUM(K21:K30) -> 0 | L20: =SUM(L21:L30) -> 0 | M20: =SUM(M21:M30) -> 0 | ... AI20: =SUM(AI21:AI30) -> 0
A21: d721df33-74ba-4cc6-85ef-abefa98e5b85 | B21: b819a9c0-df6d-41e8-a77f-2e13875e4712 | C21: 3.1.1 | D21: a.i. | E21: Arrears of Cumulative Dividends
A22: 608921b7-1017-40be-9ac7-b0842e96b22d | B22: b819a9c0-df6d-41e8-a77f-2e13875e4712 | C22: 3.1.2 | D22: ii | E22: Gratuity Liability Not Provided For
A23: 66d2dbbe-de69-408e-9f7f-de4962c2c0e6 | B23: b819a9c0-df6d-41e8-a77f-2e13875e4712 | C23: 3.1.3 | D23: iii | E23: Disputed Excise / Customs / Tax Liabilities
A24: 9415d0bd-e759-4de8-bc98-4912a316ff90 | B24: b819a9c0-df6d-41e8-a77f-2e13875e4712 | C24: 3.1.4 | D24: iv. | E24: Other liabilities not provided for
A25: afc4b84c-c2b7-40c5-8e27-1640b795df46 | B25: b819a9c0-df6d-41e8-a77f-2e13875e4712 | C25: 3.1.5 | D25: b.i. | E25: Outstanding LCs
A26: f66e3fe5-a767-415b-b422-8bd5172f99ba | B26: b819a9c0-df6d-41e8-a77f-2e13875e4712 | C26: 3.1.6 | D26: ii. | E26: Outstanding bills discounted & purchased
A27: 7c3df7a3-c623-4e07-8aa0-9bb150d158c0 | B27: b819a9c0-df6d-41e8-a77f-2e13875e4712 | C27: 3.1.7 | D27: iii. | E27: Outstanding BGs
A28: 1ccd391d-bec6-4510-b53a-54be4cd981bc | B28: b819a9c0-df6d-41e8-a77f-2e13875e4712 | C28: 3.1.8 | D28: c. | E28: Financial Guarantees issued by the company
A29: 7b9f63a7-81df-4936-843d-b562ab36499b | B29: b819a9c0-df6d-41e8-a77f-2e13875e4712 | C29: 3.1.9 | D29: d.i. | E29: Redemption premium not provided for
A30: 52f8c582-10f5-4d7b-9dae-05c0c9cb0195 | B30: b819a9c0-df6d-41e8-a77f-2e13875e4712 | C30: 3.1.10 | D30: ii. | E30: MTM loss on derivatives not provided for
A31: 56367121-7aaf-430d-8353-418a911ca699 | B31: 0dba63d6-0776-413f-8351-2f2222c3cb3f | C31: 3.2 | D31: B | E31: Crystallized losses in the year without routing through P&L account
A32: d81c68ed-0f4e-4e71-883f-560fe7f22bd9 | B32: 0dba63d6-0776-413f-8351-2f2222c3cb3f | C32: 3.3 | D32: C | E32: Accumulated depreciation on fixed assets sold/ discarded during the year
A33: 4749684c-2a79-479c-8ef0-d6f7f8ec7252 | B33: 0dba63d6-0776-413f-8351-2f2222c3cb3f | C33: 3.4 | D33: D | E33: Accumulated amortization on intangible assets sold/ discarded during the year
A34: b2eff56f-bbd6-4b5a-8510-05851535a1ba | B34: 0dba63d6-0776-413f-8351-2f2222c3cb3f | C34: 3.5 | D34: E | E34: Write-off in value of stock in process during the year | F34: ='Profit and Loss Statement'!F77 -> 0 | G34: ='Profit and Loss Statement'!G77 -> 0 | H34: ='Profit and Loss Statement'!H77 -> 0 | I34: ='Profit and Loss Statement'!I77 -> 0 | J34: ='Profit and Loss Statement'!J77 -> 0 | K34: ='Profit and Loss Statement'!K77 -> 0 | L34: ='Profit and Loss Statement'!L77 -> 0 | M34: ='Profit and Loss Statement'!M77 -> 0 | ... AI34: ='Profit and Loss Statement'!AI77 -> 0
A35: 825f0ef2-92f1-491a-826d-e2645481f1f2 | B35: 0dba63d6-0776-413f-8351-2f2222c3cb3f | C35: 3.6 | D35: F | E35: Write-off in value of finished goods during the year | F35: ='Profit and Loss Statement'!F78 -> 0 | G35: ='Profit and Loss Statement'!G78 -> 0 | H35: ='Profit and Loss Statement'!H78 -> 0 | I35: ='Profit and Loss Statement'!I78 -> 0 | J35: ='Profit and Loss Statement'!J78 -> 0 | K35: ='Profit and Loss Statement'!K78 -> 0 | L35: ='Profit and Loss Statement'!L78 -> 0 | M35: ='Profit and Loss Statement'!M78 -> 0 | ... AI35: ='Profit and Loss Statement'!AI78 -> 0

Sheet Ratios
E1: BORROWER_NAME
E2: BORROWER_CODE
A3: 988a49f2-7288-402f-99fc-87d1bf295447 | E3: TEMPLATE_NAME | F3: Company Financial Template
E4: PROJECT_NAME
E5: ACCOUNTING_TYPE
E6: FINANCIAL_TYPE
E7: YEAR
E8: YEAR_TYPE
E9: STATEMENT_DATE (YYYY-MM-DD)
E10: NO_OF_MONTHS
E11: CURRENCY
E12: DENOMINATION
E13: AUDITOR_NAME
E14: VERSION
E15: CIF_ID
E16: BASE_YEAR
F17: 1 | G17: 2 | H17: 3 | I17: 4 | J17: 5 | K17: 6 | L17: 7 | M17: 8 | N17: 9 | O17: 10 | P17: 11 | Q17: 12 | R17: 13 | S17: 14 | T17: 15 | U17: 16 | V17: 17 | W17: 18 | X17: 19 | Y17: 20 | Z17: 21 | AA17: 22 | AB17: 23 | AC17: 24 | AD17: 25 | AE17: 26 | AF17: 27 | AG17: 28 | AH17: 29 | AI17: 30
A18: UUID | B18: PARENT ID | C18: AUTO_SEQUENCE | D18: INPUT_SEQUENCE | E18: LINE_ITEM_NAME | F18: VALUE | G18: VALUE | H18: VALUE | I18: VALUE | J18: VALUE | K18: VALUE | L18: VALUE | M18: VALUE | N18: VALUE | O18: VALUE | P18: VALUE | Q18: VALUE | R18: VALUE | S18: VALUE | T18: VALUE | U18: VALUE | V18: VALUE | W18: VALUE | X18: VALUE | Y18: VALUE | Z18: VALUE | AA18: VALUE | AB18: VALUE | AC18: VALUE | AD18: VALUE | AE18: VALUE | AF18: VALUE | AG18: VALUE | AH18: VALUE | AI18: VALUE
A19: b8cf3817-536a-4500-a4a3-4d86a0a3f882 | C19: 4 | E19: Ratios
A20: 74fad8f6-8858-42dc-9dda-b4bfacb8c644 | B20: b8cf3817-536a-4500-a4a3-4d86a0a3f882 | C20: 4.1 | D20: 1 | E20: TOI
A21: 4b8ffc50-6a9b-4794-a768-490d48542485 | B21: b8cf3817-536a-4500-a4a3-4d86a0a3f882 | C21: 4.2 | D21: 2 | E21: EBIDTA
A22: 6482e5f1-6164-4430-b6e3-6578bd299e76 | B22: b8cf3817-536a-4500-a4a3-4d86a0a3f882 | C22: 4.3 | D22: 3 | E22: EBIDTA/TOI (%)
A23: dbfeabc7-6fdb-4a4a-8d8c-19b7c24afa0f | B23: b8cf3817-536a-4500-a4a3-4d86a0a3f882 | C23: 4.4 | D23: 4 | E23: Interest
A24: 8d3f273c-0938-4a47-8c87-d2da79190214 | B24: b8cf3817-536a-4500-a4a3-4d86a0a3f882 | C24: 4.5 | D24: 5 | E24: Depreciation and Amortization
A25: 51d37c1c-a3f7-44c9-bd94-6bf1a38ba12f | B25: b8cf3817-536a-4500-a4a3-4d86a0a3f882 | C25: 4.6 | D25: 6 | E25: Operating profit
A26: 77453387-fb2f-4e9a-820c-dca234ce0d7c | B26: b8cf3817-536a-4500-a4a3-4d86a0a3f882 | C26: 4.7 | D26: 7 | E26: Net non-operating income
A27: df6073c0-5418-4909-b0b3-cdb37fa69927 | B27: b8cf3817-536a-4500-a4a3-4d86a0a3f882 | C27: 4.8 | D27: 8 | E27: PBT
A28: 1584e341-e6c2-411b-aa12-b5dd6613092c | B28: b8cf3817-536a-4500-a4a3-4d86a0a3f882 | C28: 4.9 | D28: 9 | E28: PAT
A29: c199b620-e552-49e1-a9d0-3c468413c690 | B29: b8cf3817-536a-4500-a4a3-4d86a0a3f882 | C29: 4.10 | D29: 10 | E29: PAT/TOI (%)
A30: 08efe169-580d-4daa-9b58-477ade83248b | B30: b8cf3817-536a-4500-a4a3-4d86a0a3f882 | C30: 4.11 | D30: 11 | E30: NCA
A31: 6a44f956-ba1d-4799-93e6-249efeb3e389 | B31: b8cf3817-536a-4500-a4a3-4d86a0a3f882 | C31: 4.12 | D31: 12 | E31: NFA
... A34: 28c4d392-680e-43f6-856d-e7a7beb453ef | B34: b8cf3817-536a-4500-a4a3-4d86a0a3f882 | C34: 4.15 | D34: 15 | E34: Exposure in subsidiaries/Group Cos.
A35: 14cff825-5a85-4e12-8534-8d07d7039113 | B35: 28c4d392-680e-43f6-856d-e7a7beb453ef | C35: 4.15.1 | E35: Investments
A36: f68509c3-70d2-43ff-a3d4-04c467770664 | B36: 28c4d392-680e-43f6-856d-e7a7beb453ef | C36: 4.15.2 | E36: Loans and advances
A37: 0469177e-752b-49a0-9837-fb5dd1980098 | B37: b8cf3817-536a-4500-a4a3-4d86a0a3f882 | C37: 4.16 | D37: 16 | E37: Adjusted TNW (ATNW)
A38: e8f0fe7c-d8bc-4d04-b962-bd923918c71f | B38: b8cf3817-536a-4500-a4a3-4d86a0a3f882 | C38: 4.17 | D38: 17 | E38: Long term debt (LTD) (A)
A39: ece6234d-d6b2-4e97-8691-1ed4f1c5f56d | B39: b8cf3817-536a-4500-a4a3-4d86a0a3f882 | C39: 4.18 | D39: 18 | E39: Short term debt (STD) (B)
A40: ca6dcd17-f145-488b-a14d-973d169a64b5 | B40: b8cf3817-536a-4500-a4a3-4d86a0a3f882 | C40: 4.19 | E40: Term loan repayments
A41: 2b40911d-cd89-4fe7-9004-fe983994154d | B41: b8cf3817-536a-4500-a4a3-4d86a0a3f882 | C41: 4.20 | E41: Other working capital STD
A42: 8f9dfa3f-0033-49a6-8050-f14917dc09a5 | B42: b8cf3817-536a-4500-a4a3-4d86a0a3f882 | C42: 4.21 | D42: 19 | E42: WC bank finance (C)
A43: 29081440-6502-4a9d-8407-0bb2603b94a3 | B43: b8cf3817-536a-4500-a4a3-4d86a0a3f882 | C43: 4.22 | D43: 20 | E43: Total Debt (w/o Gtee) ( A+B+C)
A44: bd2a71a6-7492-40e5-bbc0-2e7edb4a1a26 | B44: b8cf3817-536a-4500-a4a3-4d86a0a3f882 | C44: 4.23 | D44: 21 | E44: Corporate Guarantee (D)
A45: fc9996c9-0701-47d9-aea5-fe90d4394517 | B45: b8cf3817-536a-4500-a4a3-4d86a0a3f882 | C45: 4.24 | D45: 22 | E45: Total Debt (A+B+C+D)
A46: 320bbfc8-14d7-42cc-a540-27c5c92873f5 | B46: b8cf3817-536a-4500-a4a3-4d86a0a3f882 | C46: 4.25 | D46: 23 | E46: Other term liabilities not considered debt
A47: 48fc2031-8952-433c-a6cc-8c17a9e24dab | B47: b8cf3817-536a-4500-a4a3-4d86a0a3f882 | C47: 4.26 | D47: 24 | E47: Total outside liabilities (TOL)
A48: 71efca45-8f00-4755-b6f4-863e567ec43d | B48: b8cf3817-536a-4500-a4a3-4d86a0a3f882 | C48: 4.27 | D48: 25 | E48: LTD/TNW (times)
A49: 432794ef-53ab-4180-9a66-c0570f27f5bb | B49: b8cf3817-536a-4500-a4a3-4d86a0a3f882 | C49: 4.28 | D49: 26 | E49: LTD/ATNW (times)
A50: 7bd69b42-2d6c-4cd0-acbe-c58f9d2d35d4 | B50: b8cf3817-536a-4500-a4a3-4d86a0a3f882 | C50: 4.29 | D50: 27 | E50: TD/TNW (times)
A51: 63477847-1b50-4fd2-b81c-b8236b8a84ff | B51: b8cf3817-536a-4500-a4a3-4d86a0a3f882 | C51: 4.30 | D51: 28 | E51: TD/ATNW (times)
A52: f22f40ca-66fc-41a2-a4a4-1f09fe18eba6 | B52: b8cf3817-536a-4500-a4a3-4d86a0a3f882 | C52: 4.31 | D52: 29 | E52: TD/EBIDTA (times)
A53: c042394f-5a3b-4a7d-8a77-45915986ba8b | B53: b8cf3817-536a-4500-a4a3-4d86a0a3f882 | C53: 4.32 | D53: 30 | E53: TD/NCA (times)
... A78: 8e6e05b1-7475-4e82-a0b3-a55aad804577 | B78: b8cf3817-536a-4500-a4a3-4d86a0a3f882 | C78: 4.57 | D78: 55 | E78: Capital Employed
A79: b4533ae6-2cf9-412f-a5d1-6c150f5fd193 | B79: b8cf3817-536a-4500-a4a3-4d86a0a3f882 | C79: 4.58
A80: 04fb6ac6-f333-40da-b759-6d114e1d2527 | B80: b8cf3817-536a-4500-a4a3-4d86a0a3f882 | C80: 4.59 | E80: Ratios for Benchmarks (Past) - RAM
A81: 4394f047-53d1-47d4-bfc5-cd0c8d8c2024 | B81: 04fb6ac6-f333-40da-b759-6d114e1d2527 | C81: 4.59.1 | E81: ROCE(%)
A82: 130e77ec-8c87-46cd-ba2c-6f3bb046d3a9 | B82: 04fb6ac6-f333-40da-b759-6d114e1d2527 | C82: 4.59.2 | E82: Operating Margin(%)
A83: 9345bcf8-6350-4cd1-ac41-25e5b2c2255e | B83: 04fb6ac6-f333-40da-b759-6d114e1d2527 | C83: 4.59.3 | E83: Interest Coverage Ratio
A84: 5325f9fd-23d7-4aa9-9b6a-b493eb86ee72 | B84: 04fb6ac6-f333-40da-b759-6d114e1d2527 | C84: 4.59.4 | E84: Tangible Networth
A85: cf53b9c5-1102-41ee-adcc-0da0280bf975 | B85: 04fb6ac6-f333-40da-b759-6d114e1d2527 | C85: 4.59.5 | E85: Total Debt / Tangible Networth
A86: 9fe9566e-ba8b-4b06-996f-e08e6da541f6 | B86: 04fb6ac6-f333-40da-b759-6d114e1d2527 | C86: 4.59.6 | E86: Net Cash Accruals / Total debt
A87: 8be721bd-ceb4-41de-9fe1-1cb7f35c1e81 | B87: 04fb6ac6-f333-40da-b759-6d114e1d2527 | C87: 4.59.7 | E87: Cash / Debt
A88: 102c5234-0350-47d2-a2ca-22442e6d7b1c | B88: 04fb6ac6-f333-40da-b759-6d114e1d2527 | C88: 4.59.8 | E88: NCA/ CPLTD
A89: 927a9aa9-179d-4479-87a2-2ff37531bce6 | B89: 04fb6ac6-f333-40da-b759-6d114e1d2527 | C89: 4.59.9 | E89: Current Ratio
A90: 1f490283-94c0-49ac-af9a-3199390c909a | B90: 04fb6ac6-f333-40da-b759-6d114e1d2527 | C90: 4.59.10 | E90: Total Outside Liabilities / Tangible Networth
A91: 7204ebdc-d75d-43eb-972f-59b48e3a0b38 | B91: 04fb6ac6-f333-40da-b759-6d114e1d2527 | C91: 4.59.11 | E91: Stability of revenue (Trend) %
... A105: 0b7c595d-491a-48cd-94f1-9c9ec29f2918 | B105: 84b40315-4270-4a83-8bec-bdd3d42e70e3 | C105: 4.60.12 | E105: Trend in cash conversion cycle %

Sheet Financial Spreading & Analysis
A1: v | E1: BORROWER_NAME
E2: BORROWER_CODE
E3: TEMPLATE_NAME | F3: Company Financial Template
E4: PROJECT_NAME
E5: ACCOUNTING_TYPE
E6: FINANCIAL_TYPE
E7: YEAR
E8: YEAR_TYPE
E9: STATEMENT_DATE (YYYY-MM-DD)
E10: NO_OF_MONTHS
E11: CURRENCY
E12: DENOMINATION
E13: AUDITOR_NAME
E14: VERSION
E15: CIF_ID
E16: BASE_YEAR
D17: BASE_YEAR | F17: -30 | G17: -29 | H17: -28 | I17: -27 | J17: -26 | K17: -25 | L17: -24 | M17: -23 | N17: -22 | O17: -21 | P17: -20 | Q17: -19 | R17: -18 | S17: -17 | T17: -16 | U17: -15 | V17: -14 | W17: -13 | X17: -12 | Y17: -11 | Z17: -10 | AA17: -9 | AB17: -8 | AC17: -7 | AD17: -6 | AE17: -5 | AF17: -4 | AG17: -3 | AH17: -2 | AI17: -1 | AJ17: 0 | AK17: 1 | AL17: 2 | AM17: 3 | AN17: 4 | AO17: 5 | AP17: 6 | AQ17: 7 | AR17: 8 | AS17: 9 | AT17: 10 | AU17: 11 | AV17: 12 | AW17: 13 | AX17: 14 | AY17: 15 | AZ17: 16 | BA17: 17 | BB17: 18 | BC17: 19 | BD17: 20 | BE17: 21 | BF17: 22 | BG17: 23 | BH17: 24 | BI17: 25 | BJ17: 26 | BK17: 27 | BL17: 28 | BM17: 29 | BN17: 30 | BO17: Projection Method Name | BP17: 1 | BQ17: 2 | BR17: 3 | BS17: 4 | BT17: 5 | BU17: 6 | BV17: 7 | BW17: 8 | BX17: 9 | BY17: 10 | BZ17: 11 | CA17: 12 | CB17: 13 | CC17: 14 | CD17: 15 | CE17: Projection Method Name | CF17: 1 | CG17: 2 | CH17: 3 | CI17: 4 | CJ17: 5 | CK17: 6 | CL17: 7 | CM17: 8 | CN17: 9 | CO17: 10 | CP17: 11 | CQ17: 12 | CR17: 13 | CS17: 14 | CT17: 15 | CU17: Projection Method Name | CV17: 1 | CW17: 2 | CX17: 3 | CY17: 4 | CZ17: 5 | DA17: 6 | DB17: 7 | DC17: 8 | DD17: 9 | DE17: 10 | DF17: 11 | DG17: 12 | DH17: 13 | DI17: 14 | DJ17: 15 | DK17: Projection Method Name | DL17: 1 | DM17: 2 | DN17: 3 | DO17: 4 | DP17: 5 | DQ17: 6 | DR17: 7 | DS17: 8 | DT17: 9 | DU17: 10 | DV17: 11 | DW17: 12 | DX17: 13 | DY17: 14 | DZ17: 15 | EA17: Projection Method Name | EB17: 1 | EC17: 2 | ED17: 3 | EE17: 4 | EF17: 5 | EG17: 6 | EH17: 7 | EI17: 8 | EJ17: 9 | EK17: 10 | EL17: 11 | EM17: 12 | EN17: 13 | EO17: 14 | EP17: 15
D18: Rating Year | E18: 2026 | BO18: MINIMUM | CE18: MAXIMUM | CU18: AVERAGE | DK18: REGRESSION | EA18: ADHOC
A20: UUID | B20: PARENT ID | C20: AUTO_SEQUENCE | D20: INPUT_SEQUENCE | E20: LINE_ITEM_NAME | F20: =SUM(E17,F17) -> -30 | G20: =SUM(E17,G17) -> -29 | H20: =SUM(E17,H17) -> -28 | I20: =SUM(E17,I17) -> -27 | J20: =SUM(E17,J17) -> -26 | K20: =SUM(E17,K17) -> -25 | L20: =SUM(E17,L17) -> -24 | M20: =SUM(E17,M17) -> -23 | N20: =SUM(E17,N17) -> -22 | O20: =SUM(E17,O17) -> -21 | P20: =SUM(E17,P17) -> -20 | Q20: =SUM(E17,Q17) -> -19 | R20: =SUM(E17,R17) -> -18 | S20: =SUM(E17,S17) -> -17 | T20: =SUM(E17,T17) -> -16 | U20: =SUM(E17,U17) -> -15 | V20: =SUM(E17,V17) -> -14 | W20: =SUM(E17,W17) -> -13 | X20: =SUM(E17,X17) -> -12 | Y20: =SUM(E17,Y17) -> -11 | Z20: =SUM(E17,Z17) -> -10 | AA20: =SUM(E17,AA17) -> -9 | AB20: =SUM(E17,AB17) -> -8 | AC20: =SUM(E17,AC17) -> -7 | AD20: =SUM(E17,AD17) -> -6 | AE20: =SUM(E17,AE17) -> -5 | AF20: =SUM(E17,AF17) -> -4 | AG20: =SUM(E17,AG17) -> -3 | AH20: =SUM(E17,AH17) -> -2 | AI20: =SUM(E17,AI17) -> -1 | AJ20: =SUM(E17,AJ17) -> 0 | AK20: =SUM(E17,AK17) -> 1 | AL20: =SUM(E17,AL17) -> 2 | AM20: =SUM(E17,AM17) -> 3 | AN20: =SUM(E17,AN17) -> 4 | AO20: =SUM(E17,AO17) -> 5 | AP20: =SUM(E17,AP17) -> 6 | AQ20: =SUM(E17,AQ17) -> 7 | AR20: =SUM(E17,AR17) -> 8 | AS20: =SUM(E17,AS17) -> 9 | AT20: =SUM(E17,AT17) -> 10 | AU20: =SUM(E17,AU17) -> 11 | AV20: =SUM(E17,AV17) -> 12 | AW20: =SUM(E17,AW17) -> 13 | AX20: =SUM(E17,AX17) -> 14 | AY20: =SUM(E17,AY17) -> 15 | AZ20: =SUM(E17,AZ17) -> 16 | BA20: =SUM(E17,BA17) -> 17 | BB20: =SUM(E17,BB17) -> 18 | BC20: =SUM(E17,BC17) -> 19 | BD20: =SUM(E17,BD17) -> 20 | BE20: =SUM(E17,BE17) -> 21 | BF20: =SUM(E17,BF17) -> 22 | BG20: =SUM(E17,BG17) -> 23 | BH20: =SUM(E17,BH17) -> 24 | BI20: =SUM(E17,BI17) -> 25 | BJ20: =SUM(E17,BJ17) -> 26 | BK20: =SUM(E17,BK17) -> 27 | BL20: =SUM(E17,BL17) -> 28 | BM20: =SUM(E17,BM17) -> 29 | BN20: =SUM(E17,BN17) -> 30 | BP20: =SUM(E17,BP17) -> 1 | BQ20: =SUM(E17,BQ17) -> 2 | BR20: =SUM(E17,BR17) -> 3 | BS20: =SUM(E17,BS17) -> 4 | BT20: =SUM(E17,BT17) -> 5 | BU20: =SUM(E17,BU17) -> 6 | BV20: =SUM(E17,BV17) -> 7 | BW20: =SUM(E17,BW17) -> 8 | BX20: =SUM(E17,BX17) -> 9 | BY20: =SUM(E17,BY17) -> 10 | BZ20: =SUM(E17,BZ17) -> 11 | CA20: =SUM(E17,CA17) -> 12 | CB20: =SUM(E17,CB17) -> 13 | CC20: =SUM(E17,CC17) -> 14 | CD20: =SUM(E17,CD17) -> 15 | CF20: =SUM(E17,CF17) -> 1 | CG20: =SUM(E17,CG17) -> 2 | CH20: =SUM(E17,CH17) -> 3 | CI20: =SUM(E17,CI17) -> 4 | CJ20: =SUM(E17,CJ17) -> 5 | CK20: =SUM(E17,CK17) -> 6 | CL20: =SUM(E17,CL17) -> 7 | CM20: =SUM(E17,CM17) -> 8 | CN20: =SUM(E17,CN17) -> 9 | CO20: =SUM(E17,CO17) -> 10 | CP20: =SUM(E17,CP17) -> 11 | CQ20: =SUM(E17,CQ17) -> 12 | CR20: =SUM(E17,CR17) -> 13 | CS20: =SUM(E17,CS17) -> 14 | CT20: =SUM(E17,CT17) -> 15 | CV20: =SUM(E17,CV17) -> 1 | CW20: =SUM(E17,CW17) -> 2 | CX20: =SUM(E17,CX17) -> 3 | CY20: =SUM(E17,CY17) -> 4 | CZ20: =SUM(E17,CZ17) -> 5 | DA20: =SUM(E17,DA17) -> 6 | DB20: =SUM(E17,DB17) -> 7 | DC20: =SUM(E17,DC17) -> 8 | DD20: =SUM(E17,DD17) -> 9 | DE20: =SUM(E17,DE17) -> 10 | DF20: =SUM(E17,DF17) -> 11 | DG20: =SUM(E17,DG17) -> 12 | DH20: =SUM(E17,DH17) -> 13 | DI20: =SUM(E17,DI17) -> 14 | DJ20: =SUM(E17,DJ17) -> 15 | DL20: =SUM(E17,DL17) -> 1 | DM20: =SUM(E17,DM17) -> 2 | DN20: =SUM(E17,DN17) -> 3 | DO20: =SUM(E17,DO17) -> 4 | DP20: =SUM(E17,DP17) -> 5 | DQ20: =SUM(E17,DQ17) -> 6 | DR20: =SUM(E17,DR17) -> 7 | DS20: =SUM(E17,DS17) -> 8 | DT20: =SUM(E17,DT17) -> 9 | DU20: =SUM(E17,DU17) -> 10 | DV20: =SUM(E17,DV17) -> 11 | DW20: =SUM(E17,DW17) -> 12 | DX20: =SUM(E17,DX17) -> 13 | DY20: =SUM(E17,DY17) -> 14 | DZ20: =SUM(E17,DZ17) -> 15 | EB20: =SUM(E17,EB17) -> 1 | EC20: =SUM(E17,EC17) -> 2 | ED20: =SUM(E17,ED17) -> 3 | EE20: =SUM(E17,EE17) -> 4 | EF20: =SUM(E17,EF17) -> 5 | EG20: =SUM(E17,EG17) -> 6 | EH20: =SUM(E17,EH17) -> 7 | EI20: =SUM(E17,EI17) -> 8 | EJ20: =SUM(E17,EJ17) -> 9 | EK20: =SUM(E17,EK17) -> 10 | EL20: =SUM(E17,EL17) -> 11 | EM20: =SUM(E17,EM17) -> 12 | EN20: =SUM(E17,EN17) -> 13 | EO20: =SUM(E17,EO17) -> 14 | EP20: =SUM(E17,EP17) -> 15
A21: c98dd930-c06b-4184-a258-ac39cd19a193 | C21: 1 | E21: Profit and Loss Statement
A22: 10a60949-9659-4ea4-b1c3-1f16074a2874 | B22: c98dd930-c06b-4184-a258-ac39cd19a193 | C22: 1.1 | D22: 1 | E22: Gross Sales
A23: 1fe0fddb-2578-4028-bb64-bd63d70cdd09 | B23: 10a60949-9659-4ea4-b1c3-1f16074a2874 | C23: 1.1.1 | D23: 1.1 | E23: Domestic Sales
A24: 725d10e1-e2a6-4996-b9d0-4ad6ffc75b68 | B24: 10a60949-9659-4ea4-b1c3-1f16074a2874 | C24: 1.1.2 | D24: 1.2 | E24: Export Sales
A25: 640dbfc9-deeb-44e3-9198-96949e0cae58 | B25: 10a60949-9659-4ea4-b1c3-1f16074a2874 | C25: 1.1.3 | D25: 1.3 | E25: Total | F25: =ROUND(SUM(F$23:F$24),2) -> 0 | G25: =ROUND(SUM(G$23:G$24),2) -> 0 | H25: =ROUND(SUM(H$23:H$24),2) -> 0 | I25: =ROUND(SUM(I$23:I$24),2) -> 0 | J25: =ROUND(SUM(J$23:J$24),2) -> 0 | K25: =ROUND(SUM(K$23:K$24),2) -> 0 | L25: =ROUND(SUM(L$23:L$24),2) -> 0 | M25: =ROUND(SUM(M$23:M$24),2) -> 0 | ... BN25: =ROUND(SUM(BN$23:BN$24),2) -> 0
A26: 59b1facc-2b05-4ef0-bd3c-52d6156b19af | B26: c98dd930-c06b-4184-a258-ac39cd19a193 | C26: 1.2 | D26: 2 | E26: Less Excise Duty
A27: a3c6e8f3-99c4-41a0-adec-acb5ff2f3b00 | B27: c98dd930-c06b-4184-a258-ac39cd19a193 | C27: 1.3 | D27: 3 | E27: Net Sales (1 - 2) | F27: =ROUND(F25-F26,2) -> 0 | G27: =ROUND(G25-G26,2) -> 0 | H27: =ROUND(H25-H26,2) -> 0 | I27: =ROUND(I25-I26,2) -> 0 | J27: =ROUND(J25-J26,2) -> 0 | K27: =ROUND(K25-K26,2) -> 0 | L27: =ROUND(L25-L26,2) -> 0 | M27: =ROUND(M25-M26,2) -> 0 | ... BN27: =ROUND(BN25-BN26,2) -> 0
A28: 48b561dd-2f32-4bf9-9890-f458e178e892 | B28: c98dd930-c06b-4184-a258-ac39cd19a193 | C28: 1.4 | E28: % age rise (+) or fall (-) in net sales as compared to previous year (annualised) | G28: =IF(F27=0,0,IF(G27=0,0,((G27/G10)-(F27/F10))/(F27/F10))*100) -> 0 | H28: =IF(G27=0,0,IF(H27=0,0,((H27/H10)-(G27/G10))/(G27/G10))*100) -> 0 | I28: =IF(H27=0,0,IF(I27=0,0,((I27/I10)-(H27/H10))/(H27/H10))*100) -> 0 | J28: =IF(I27=0,0,IF(J27=0,0,((J27/J10)-(I27/I10))/(I27/I10))*100) -> 0 | K28: =IF(J27=0,0,IF(K27=0,0,((K27/K10)-(J27/J10))/(J27/J10))*100) -> 0 | L28: =IF(K27=0,0,IF(L27=0,0,((L27/L10)-(K27/K10))/(K27/K10))*100) -> 0 | M28: =IF(L27=0,0,IF(M27=0,0,((M27/M10)-(L27/L10))/(L27/L10))*100) -> 0 | N28: =IF(M27=0,0,IF(N27=0,0,((N27/N10)-(M27/M10))/(M27/M10))*100) -> 0 | ... BN28: =IF(BM27=0,0,IF(BN27=0,0,((BN27/BN10)-(BM27/BM10))/(BM27/BM10))*100) -> 0
A29: 16c1b0ac-ba37-4ed6-bb75-c0d4993e9ae8 | B29: c98dd930-c06b-4184-a258-ac39cd19a193 | C29: 1.5 | E29: Other recurring income incidental to main business
A30: 758d688a-abd2-4efa-bace-54c0f837efaa | B30: c98dd930-c06b-4184-a258-ac39cd19a193 | C30: 1.6 | D30: 4 | E30: Total operating income | F30: =F27+F29 -> 0 | G30: =G27+G29 -> 0 | H30: =H27+H29 -> 0 | I30: =I27+I29 -> 0 | J30: =J27+J29 -> 0 | K30: =K27+K29 -> 0 | L30: =L27+L29 -> 0 | M30: =M27+M29 -> 0 | ... BN30: =BN27+BN29 -> 0
A31: 03e7d409-963e-4698-9508-323cb4718bd7 | B31: c98dd930-c06b-4184-a258-ac39cd19a193 | C31: 1.7 | D31: 5 | E31: Cost of Sales
A32: 3d4377af-5b9d-4fc5-8ad3-56f2be931ed3 | B32: 03e7d409-963e-4698-9508-323cb4718bd7 | C32: 1.7.1 | D32: i. | E32: Raw materials | F32: =ROUND(SUM(F$33:F$34),2) -> 0 | G32: =ROUND(SUM(G$33:G$34),2) -> 0 | H32: =ROUND(SUM(H$33:H$34),2) -> 0 | I32: =ROUND(SUM(I$33:I$34),2) -> 0 | J32: =ROUND(SUM(J$33:J$34),2) -> 0 | K32: =ROUND(SUM(K$33:K$34),2) -> 0 | L32: =ROUND(SUM(L$33:L$34),2) -> 0 | M32: =ROUND(SUM(M$33:M$34),2) -> 0 | ... BN32: =ROUND(SUM(BN$33:BN$34),2) -> 0
A33: d4fd265c-aebb-4d35-8d34-fbb90f8879b1 | B33: 3d4377af-5b9d-4fc5-8ad3-56f2be931ed3 | C33: 1.7.1.1 | D33: a. | E33: i) Imported
A34: 196afb1b-3271-4e26-8c17-a1687f1442a1 | B34: 3d4377af-5b9d-4fc5-8ad3-56f2be931ed3 | C34: 1.7.1.2 | D34: b. | E34: ii) Indigenous
A35: b5374b98-fbc9-4afd-91a6-687949a4353a | B35: 03e7d409-963e-4698-9508-323cb4718bd7 | C35: 1.7.2 | D35: ii. | E35: Other Spares
A36: f78f861b-e42f-4c79-b4df-5106e411ae92 | B36: 03e7d409-963e-4698-9508-323cb4718bd7 | C36: 1.7.3 | D36: iii. | E36: Power and Fuel
A37: 148302c9-c702-4281-9fb6-424bb1a09513 | B37: 03e7d409-963e-4698-9508-323cb4718bd7 | C37: 1.7.4 | D37: iv. | E37: Direct Labour (Factory wages & salaries)
A38: a8cd1b47-c726-4920-a36e-c957dd5e4e35 | B38: 03e7d409-963e-4698-9508-323cb4718bd7 | C38: 1.7.5 | D38: v. | E38: Other manufacturing expenses | F38: =ROUND(SUM(F$39:F$41),2) -> 0 | G38: =ROUND(SUM(G$39:G$41),2) -> 0 | H38: =ROUND(SUM(H$39:H$41),2) -> 0 | I38: =ROUND(SUM(I$39:I$41),2) -> 0 | J38: =ROUND(SUM(J$39:J$41),2) -> 0 | K38: =ROUND(SUM(K$39:K$41),2) -> 0 | L38: =ROUND(SUM(L$39:L$41),2) -> 0 | M38: =ROUND(SUM(M$39:M$41),2) -> 0 | ... BN38: =ROUND(SUM(BN$39:BN$41),2) -> 0
A39: 668ded41-a4aa-46a3-9c6a-800d00837629 | B39: a8cd1b47-c726-4920-a36e-c957dd5e4e35 | C39: 1.7.5.1 | D39: a. | E39: Processing / Job Work Charges
A40: 0ad52017-0aff-4518-ab1c-4f3090d51d34 | B40: a8cd1b47-c726-4920-a36e-c957dd5e4e35 | C40: 1.7.5.2 | D40: b. | E40: Freight and Transportation Charges
A41: 4920a1ca-7f77-41b8-b737-00b8b1672a4b | B41: a8cd1b47-c726-4920-a36e-c957dd5e4e35 | C41: 1.7.5.3 | D41: c. | E41: Others
A42: 0fe0bf01-2780-473f-9a02-0a0192c5ff6c | B42: 03e7d409-963e-4698-9508-323cb4718bd7 | C42: 1.7.6 | D42: vi a. | E42: Depreciation
A43: 2ac2e554-12a8-4d5f-a550-f4d76440b480 | B43: 03e7d409-963e-4698-9508-323cb4718bd7 | C43: 1.7.7 | D43: vi b. | E43: Amortization
A44: 1355a8e0-0532-4764-aaf9-5bcf329b1f83 | B44: 03e7d409-963e-4698-9508-323cb4718bd7 | C44: 1.7.8 | D44: vii | E44: Changes in inventory
A45: 36b81d10-11d4-409b-ab6a-458f6aee2219 | B45: 03e7d409-963e-4698-9508-323cb4718bd7 | C45: 1.7.9 | D45: viii. | E45: Sub-total (Total Cost of Sales) | F45: =ROUND(F36+F37+F44+F43+F42+F32+F35+F38,2) -> 0 | G45: =ROUND(G36+G37+G44+G43+G42+G32+G35+G38,2) -> 0 | H45: =ROUND(H36+H37+H44+H43+H42+H32+H35+H38,2) -> 0 | I45: =ROUND(I36+I37+I44+I43+I42+I32+I35+I38,2) -> 0 | J45: =ROUND(J36+J37+J44+J43+J42+J32+J35+J38,2) -> 0 | K45: =ROUND(K36+K37+K44+K43+K42+K32+K35+K38,2) -> 0 | L45: =ROUND(L36+L37+L44+L43+L42+L32+L35+L38,2) -> 0 | M45: =ROUND(M36+M37+M44+M43+M42+M32+M35+M38,2) -> 0 | ... BN45: =ROUND(BN36+BN37+BN44+BN43+BN42+BN32+BN35+BN38,2) -> 0
A46: d45d21cc-efc2-48d8-9d50-f166592f07f1 | B46: c98dd930-c06b-4184-a258-ac39cd19a193 | C46: 1.8 | D46: 6 | E46: Selling, general and administrative expenses | F46: =ROUND(SUM(F$47:F$57),2) -> 0 | G46: =ROUND(SUM(G$47:G$57),2) -> 0 | H46: =ROUND(SUM(H$47:H$57),2) -> 0 | I46: =ROUND(SUM(I$47:I$57),2) -> 0 | J46: =ROUND(SUM(J$47:J$57),2) -> 0 | K46: =ROUND(SUM(K$47:K$57),2) -> 0 | L46: =ROUND(SUM(L$47:L$57),2) -> 0 | M46: =ROUND(SUM(M$47:M$57),2) -> 0 | ... BN46: =ROUND(SUM(BN$47:BN$57),2) -> 0
A47: 2ef29c6a-8a7b-40e5-99c8-f89d9057243d | B47: d45d21cc-efc2-48d8-9d50-f166592f07f1 | C47: 1.8.1 | D47: a. | E47: Salary and staff expenses
A48: 2b68097c-b2d9-4814-b640-8029f0ca3ee4 | B48: d45d21cc-efc2-48d8-9d50-f166592f07f1 | C48: 1.8.2 | D48: b. | E48: Rent , Rates and Taxes
A49: 92aa2ec4-8a3c-4dbd-a197-ac3010cfc6d0 | B49: d45d21cc-efc2-48d8-9d50-f166592f07f1 | C49: 1.8.3 | D49: c. | E49: Lease rentals
A50: 70247812-1813-4670-b601-64da36a5258c | B50: d45d21cc-efc2-48d8-9d50-f166592f07f1 | C50: 1.8.4 | D50: d. | E50: Bad Debts
A51: 95e087db-f388-4a0a-9b9c-a87952212d64 | B51: d45d21cc-efc2-48d8-9d50-f166592f07f1 | C51: 1.8.5 | D51: e. | E51: Travelling & conveyance expenses
A52: 5a538d85-7501-4bcb-9624-8aebed73725d | B52: d45d21cc-efc2-48d8-9d50-f166592f07f1 | C52: 1.8.6 | D52: f. | E52: Advertisements and Sales Promotions
A53: f67c6972-1353-40e1-bcd7-1f1677bb7d3f | B53: d45d21cc-efc2-48d8-9d50-f166592f07f1 | C53: 1.8.7 | D53: g. | E53: Commission, discount & service charges
A54: 1863177f-a897-4a90-9a52-cc92f1986683 | B54: d45d21cc-efc2-48d8-9d50-f166592f07f1 | C54: 1.8.8 | D54: h. | E54: Legal & professional charges
A55: b5e1aae4-d350-417d-b95a-0c414c79e8e4 | B55: d45d21cc-efc2-48d8-9d50-f166592f07f1 | C55: 1.8.9 | D55: i. | E55: Directors remuneration
A56: 09c75130-6fcc-4aba-8999-33139f25d705 | B56: d45d21cc-efc2-48d8-9d50-f166592f07f1 | C56: 1.8.10 | D56: i. | E56: Auditors remuneration
A57: a8430eea-7c67-48ef-a1fb-72efd678b52b | B57: d45d21cc-efc2-48d8-9d50-f166592f07f1 | C57: 1.8.11 | D57: k | E57: Others
A58: 09ff9a1a-9720-422c-92fa-c3452fe2a4ed | B58: c98dd930-c06b-4184-a258-ac39cd19a193 | C58: 1.9 | D58: 7 | E58: Sub-total (5 + 6) | F58: =ROUND(F45+F46,2) -> 0 | G58: =ROUND(G45+G46,2) -> 0 | H58: =ROUND(H45+H46,2) -> 0 | I58: =ROUND(I45+I46,2) -> 0 | J58: =ROUND(J45+J46,2) -> 0 | K58: =ROUND(K45+K46,2) -> 0 | L58: =ROUND(L45+L46,2) -> 0 | M58: =ROUND(M45+M46,2) -> 0 | ... BN58: =ROUND(BN45+BN46,2) -> 0
A59: cd32dec1-9487-4fad-b68d-84929baa6c70 | B59: c98dd930-c06b-4184-a258-ac39cd19a193 | C59: 1.10 | D59: 8 | E59: Operating Profit before Interest (3 - 7) | F59: =ROUND(F30-F58,2) -> 0 | G59: =ROUND(G30-G58,2) -> 0 | H59: =ROUND(H30-H58,2) -> 0 | I59: =ROUND(I30-I58,2) -> 0 | J59: =ROUND(J30-J58,2) -> 0 | K59: =ROUND(K30-K58,2) -> 0 | L59: =ROUND(L30-L58,2) -> 0 | M59: =ROUND(M30-M58,2) -> 0 | ... BN59: =ROUND(BN30-BN58,2) -> 0
A60: 3c191bb5-9e45-49e9-92d8-62eac4a46fee | B60: c98dd930-c06b-4184-a258-ac39cd19a193 | C60: 1.11 | D60: 9 | E60: Interest | F60: =ROUND(SUM(F$61:F$63),2) -> 0 | G60: =ROUND(SUM(G$61:G$63),2) -> 0 | H60: =ROUND(SUM(H$61:H$63),2) -> 0 | I60: =ROUND(SUM(I$61:I$63),2) -> 0 | J60: =ROUND(SUM(J$61:J$63),2) -> 0 | K60: =ROUND(SUM(K$61:K$63),2) -> 0 | L60: =ROUND(SUM(L$61:L$63),2) -> 0 | M60: =ROUND(SUM(M$61:M$63),2) -> 0 | ... BN60: =ROUND(SUM(BN$61:BN$63),2) -> 0
A61: 4ac021e9-a288-49cb-8065-f08ce0d20a4b | B61: 3c191bb5-9e45-49e9-92d8-62eac4a46fee | C61: 1.11.1 | D61: a. | E61: Interest on Fixed Loans / Term loans
A62: 9d8baeb0-9b8d-4484-a719-47c3465e519d | B62: 3c191bb5-9e45-49e9-92d8-62eac4a46fee | C62: 1.11.2 | D62: b. | E62: Interest on Working capital loans
A63: 69206450-c21c-435c-ad96-06f800c1faee | B63: 3c191bb5-9e45-49e9-92d8-62eac4a46fee | C63: 1.11.3 | D63: c. | E63: Bank charges
A64: ef40fe86-94a1-411c-939f-2c4630b12982 | B64: c98dd930-c06b-4184-a258-ac39cd19a193 | C64: 1.12 | D64: 10 | E64: Operating Profit after Interest (8 - 9) | F64: =ROUND(F59-F60,2) -> 0 | G64: =ROUND(G59-G60,2) -> 0 | H64: =ROUND(H59-H60,2) -> 0 | I64: =ROUND(I59-I60,2) -> 0 | J64: =ROUND(J59-J60,2) -> 0 | K64: =ROUND(K59-K60,2) -> 0 | L64: =ROUND(L59-L60,2) -> 0 | M64: =ROUND(M59-M60,2) -> 0 | ... BN64: =ROUND(BN59-BN60,2) -> 0
A65: 1da9011e-e747-4ddc-a385-ab468c3d2848 | B65: c98dd930-c06b-4184-a258-ac39cd19a193 | C65: 1.13 | D65: 11 | E65: Add: Other non-operating Income
A66: 7922b178-da65-4ac7-9731-fd221f980f61 | B66: c98dd930-c06b-4184-a258-ac39cd19a193 | C66: 1.14 | D66: i. | E66: CASH ITEMS
A67: 73dec465-413e-426d-a2cc-dafce9007d2f | B67: 7922b178-da65-4ac7-9731-fd221f980f61 | C67: 1.14.1 | D67: a. | E67: Interest received
A68: 3c9cb6ec-b0b9-429e-8fb6-cf30cf358322 | B68: 7922b178-da65-4ac7-9731-fd221f980f61 | C68: 1.14.2 | D68: b. | E68: Dividends received from Companies
A69: f5404e9a-501d-4beb-8c52-a66cf3f2809c | B69: 7922b178-da65-4ac7-9731-fd221f980f61 | C69: 1.14.3 | D69: c | E69: Profit on sale of fixed assets / Investments
A70: ef45beb9-e0f1-4a75-ac2e-cd6ec751b34f | B70: 7922b178-da65-4ac7-9731-fd221f980f61 | C70: 1.14.4 | D70: d | E70: Misc Income
A71: 00fb8424-56dd-4bba-ab26-a02941464019 | B71: 7922b178-da65-4ac7-9731-fd221f980f61 | C71: 1.14.5 | E71: Sub-total (Non operating income - Cash) | F71: =ROUND(SUM(F$67:F$70),2) -> 0 | G71: =ROUND(SUM(G$67:G$70),2) -> 0 | H71: =ROUND(SUM(H$67:H$70),2) -> 0 | I71: =ROUND(SUM(I$67:I$70),2) -> 0 | J71: =ROUND(SUM(J$67:J$70),2) -> 0 | K71: =ROUND(SUM(K$67:K$70),2) -> 0 | L71: =ROUND(SUM(L$67:L$70),2) -> 0 | M71: =ROUND(SUM(M$67:M$70),2) -> 0 | ... BN71: =ROUND(SUM(BN$67:BN$70),2) -> 0
A72: 200cdc67-6a5a-43e0-a8d4-b820eacb321a | B72: 7922b178-da65-4ac7-9731-fd221f980f61 | C72: 1.14.6 | E72: NON CASH ITEMS
A73: fb1d0130-8c1f-414f-9293-03c94a1c0ade | B73: 200cdc67-6a5a-43e0-a8d4-b820eacb321a | C73: 1.14.6.1 | D73: a. | E73: {Others}
A74: 50e3e6b1-ca92-4e82-b2ca-b0b8426846e5 | B74: 200cdc67-6a5a-43e0-a8d4-b820eacb321a | C74: 1.14.6.2 | E74: Sub-total (Non operating income - Non-cash) | F74: =ROUND(SUM(F$73),2) -> 0 | G74: =ROUND(SUM(G$73),2) -> 0 | H74: =ROUND(SUM(H$73),2) -> 0 | I74: =ROUND(SUM(I$73),2) -> 0 | J74: =ROUND(SUM(J$73),2) -> 0 | K74: =ROUND(SUM(K$73),2) -> 0 | L74: =ROUND(SUM(L$73),2) -> 0 | M74: =ROUND(SUM(M$73),2) -> 0 | ... BN74: =ROUND(SUM(BN$73),2) -> 0
A75: 11fa2e28-79b1-4b4e-af42-e071c9bd2d50 | B75: 200cdc67-6a5a-43e0-a8d4-b820eacb321a | C75: 1.14.6.3 | E75: Sub-total (Non operating Income) | F75: =ROUND(F71+F74,2) -> 0 | G75: =ROUND(G71+G74,2) -> 0 | H75: =ROUND(H71+H74,2) -> 0 | I75: =ROUND(I71+I74,2) -> 0 | J75: =ROUND(J71+J74,2) -> 0 | K75: =ROUND(K71+K74,2) -> 0 | L75: =ROUND(L71+L74,2) -> 0 | M75: =ROUND(M71+M74,2) -> 0 | ... BN75: =ROUND(BN71+BN74,2) -> 0
A76: c8016418-d641-48e5-bf69-9b5c6c31110f | B76: 7922b178-da65-4ac7-9731-fd221f980f61 | C76: 1.14.7 | D76: ii. | E76: Deduct: Other non-operating expenses
A77: dd04bf42-b0b2-4c61-8fdd-e65dca71901a | B77: 7922b178-da65-4ac7-9731-fd221f980f61 | C77: 1.14.8 | E77: CASH ITEMS
A78: c84141dc-2e53-4610-a1de-49f74b5bd005 | B78: dd04bf42-b0b2-4c61-8fdd-e65dca71901a | C78: 1.14.8.1 | D78: a. | E78: Crystallized forex loss
A79: 06ee36ea-0c23-4f01-a7d0-a0934ac6fd95 | B79: dd04bf42-b0b2-4c61-8fdd-e65dca71901a | C79: 1.14.8.2 | D79: b. | E79: Write-off of stock-in-process
A80: a839c66b-a310-46bc-a5b7-f502894065cc | B80: dd04bf42-b0b2-4c61-8fdd-e65dca71901a | C80: 1.14.8.3 | D80: c. | E80: Write-off of finished goods
A81: 5b9635ac-d769-4604-8838-145ae69d8c65 | B81: dd04bf42-b0b2-4c61-8fdd-e65dca71901a | C81: 1.14.8.4 | D81: d. | E81: Loss on sale of fixed assets / Investments
A82: 3eb201cc-56e5-4c0f-a24d-1b1b14fda065 | B82: dd04bf42-b0b2-4c61-8fdd-e65dca71901a | C82: 1.14.8.5 | D82: e. | E82: Other non operating cash expenses
A83: d0da1235-e20b-4bca-9be7-8c9237fbf7bc | B83: dd04bf42-b0b2-4c61-8fdd-e65dca71901a | C83: 1.14.8.6 | D83: f | E83: Other non operating cash exp
A84: f9e04cd8-943b-4010-acdb-bc999d78ce72 | B84: dd04bf42-b0b2-4c61-8fdd-e65dca71901a | C84: 1.14.8.7 | E84: Sub-total (Non operating expense -Cash) | F84: =ROUND(SUM(F$78:F$83),2) -> 0 | G84: =ROUND(SUM(G$78:G$83),2) -> 0 | H84: =ROUND(SUM(H$78:H$83),2) -> 0 | I84: =ROUND(SUM(I$78:I$83),2) -> 0 | J84: =ROUND(SUM(J$78:J$83),2) -> 0 | K84: =ROUND(SUM(K$78:K$83),2) -> 0 | L84: =ROUND(SUM(L$78:L$83),2) -> 0 | M84: =ROUND(SUM(M$78:M$83),2) -> 0 | ... BN84: =ROUND(SUM(BN$78:BN$83),2) -> 0
A85: 5d56acf7-0293-4e08-86d3-aaba02132db9 | B85: dd04bf42-b0b2-4c61-8fdd-e65dca71901a | C85: 1.14.8.8 | E85: NON CASH ITEMS
A86: 0f051e4a-a41b-4a99-88c9-feb2365cc72d | B86: 5d56acf7-0293-4e08-86d3-aaba02132db9 | C86: 1.14.8.8.1 | D86: a. | E86: MTM forex loss
A87: d8ec163d-78ac-431c-99e1-8ace8169b883 | B87: 5d56acf7-0293-4e08-86d3-aaba02132db9 | C87: 1.14.8.8.2 | D87: b. | E87: {Others}
A88: 7544d25b-0a55-4517-9df3-cd49a0af62c2 | B88: 5d56acf7-0293-4e08-86d3-aaba02132db9 | C88: 1.14.8.8.3 | E88: Sub-total (Non operating expense - Non-cash) | F88: =ROUND(SUM(F$86:F$87),2) -> 0 | G88: =ROUND(SUM(G$86:G$87),2) -> 0 | H88: =ROUND(SUM(H$86:H$87),2) -> 0 | I88: =ROUND(SUM(I$86:I$87),2) -> 0 | J88: =ROUND(SUM(J$86:J$87),2) -> 0 | K88: =ROUND(SUM(K$86:K$87),2) -> 0 | L88: =ROUND(SUM(L$86:L$87),2) -> 0 | M88: =ROUND(SUM(M$86:M$87),2) -> 0 | ... BN88: =ROUND(SUM(BN$86:BN$87),2) -> 0
A89: 522e2580-1284-415b-8016-2e703f8cee1c | B89: 5d56acf7-0293-4e08-86d3-aaba02132db9 | C89: 1.14.8.8.4 | E89: Sub-total (Non operating expense) | F89: =ROUND(F84+F88,2) -> 0 | G89: =ROUND(G84+G88,2) -> 0 | H89: =ROUND(H84+H88,2) -> 0 | I89: =ROUND(I84+I88,2) -> 0 | J89: =ROUND(J84+J88,2) -> 0 | K89: =ROUND(K84+K88,2) -> 0 | L89: =ROUND(L84+L88,2) -> 0 | M89: =ROUND(M84+M88,2) -> 0 | ... BN89: =ROUND(BN84+BN88,2) -> 0
A90: 84430ae4-7ba5-4ad1-a312-88536b3cc13c | B90: dd04bf42-b0b2-4c61-8fdd-e65dca71901a | C90: 1.14.8.9 | D90: iii | E90: Net of other non-operating income/expenses | F90: =ROUND(F75-F89,2) -> 0 | G90: =ROUND(G75-G89,2) -> 0 | H90: =ROUND(H75-H89,2) -> 0 | I90: =ROUND(I75-I89,2) -> 0 | J90: =ROUND(J75-J89,2) -> 0 | K90: =ROUND(K75-K89,2) -> 0 | L90: =ROUND(L75-L89,2) -> 0 | M90: =ROUND(M75-M89,2) -> 0 | ... BN90: =ROUND(BN75-BN89,2) -> 0
A91: fc317b2b-949e-4375-b1dd-395b77975d15 | B91: c98dd930-c06b-4184-a258-ac39cd19a193 | C91: 1.15 | D91: 12 | E91: Profit before tax/loss [10 + 11(iii)] (PBT) | F91: =ROUND(F64+F90,2) -> 0 | G91: =ROUND(G64+G90,2) -> 0 | H91: =ROUND(H64+H90,2) -> 0 | I91: =ROUND(I64+I90,2) -> 0 | J91: =ROUND(J64+J90,2) -> 0 | K91: =ROUND(K64+K90,2) -> 0 | L91: =ROUND(L64+L90,2) -> 0 | M91: =ROUND(M64+M90,2) -> 0 | ... BN91: =ROUND(BN64+BN90,2) -> 0
A92: bef66092-7c0a-4b22-baf3-56e38869958e | B92: c98dd930-c06b-4184-a258-ac39cd19a193 | C92: 1.16 | D92: 13 | E92: Provision for taxes | F92: =(ROUND(SUM(F$93:F$94),2)) -> 0 | G92: =(ROUND(SUM(G$93:G$94),2)) -> 0 | H92: =(ROUND(SUM(H$93:H$94),2)) -> 0 | I92: =(ROUND(SUM(I$93:I$94),2)) -> 0 | J92: =(ROUND(SUM(J$93:J$94),2)) -> 0 | K92: =(ROUND(SUM(K$93:K$94),2)) -> 0 | L92: =(ROUND(SUM(L$93:L$94),2)) -> 0 | M92: =(ROUND(SUM(M$93:M$94),2)) -> 0 | ... BN92: =(ROUND(SUM(BN$93:BN$94),2)) -> 0
A93: 93833f29-6945-4c8d-af99-31a624848bec | B93: bef66092-7c0a-4b22-baf3-56e38869958e | C93: 1.16.1 | D93: a. | E93: Current tax
A94: ff1fef25-6e87-4bf7-ada2-bca6a29add91 | B94: bef66092-7c0a-4b22-baf3-56e38869958e | C94: 1.16.2 | D94: b. | E94: Deferred tax
A95: 7f24fe60-dfc6-4c6c-b7a4-fed231550438 | B95: c98dd930-c06b-4184-a258-ac39cd19a193 | C95: 1.17 | D95: 14 | E95: Net Profit / Loss (12 -13) (PAT) | F95: =ROUND(F91-F92,2) -> 0 | G95: =ROUND(G91-G92,2) -> 0 | H95: =ROUND(H91-H92,2) -> 0 | I95: =ROUND(I91-I92,2) -> 0 | J95: =ROUND(J91-J92,2) -> 0 | K95: =ROUND(K91-K92,2) -> 0 | L95: =ROUND(L91-L92,2) -> 0 | M95: =ROUND(M91-M92,2) -> 0 | ... BN95: =ROUND(BN91-BN92,2) -> 0
A96: f698f49b-d41b-4833-9daf-e9b2433213db | B96: c98dd930-c06b-4184-a258-ac39cd19a193 | C96: 1.18 | D96: 15 a. | E96: Equity dividend (paid+proposed)
A97: 90548b2b-fa7b-4d84-905a-80961d65a149 | B97: c98dd930-c06b-4184-a258-ac39cd19a193 | C97: 1.19 | D97: b. | E97: Dividend Rate (% age)
A98: 44fbb444-33a1-43f0-83d6-6a66783798d6 | B98: c98dd930-c06b-4184-a258-ac39cd19a193 | C98: 1.20 | D98: 16 | E98: Retained Profit (14 - 15) | F98: =ROUND(F95-F96,2) -> 0 | G98: =ROUND(G95-G96,2) -> 0 | H98: =ROUND(H95-H96,2) -> 0 | I98: =ROUND(I95-I96,2) -> 0 | J98: =ROUND(J95-J96,2) -> 0 | K98: =ROUND(K95-K96,2) -> 0 | L98: =ROUND(L95-L96,2) -> 0 | M98: =ROUND(M95-M96,2) -> 0 | ... BN98: =ROUND(BN95-BN96,2) -> 0
A99: f5b4ddaf-88ee-4c00-95d9-5d29d2f84f13 | B99: c98dd930-c06b-4184-a258-ac39cd19a193 | C99: 1.21 | D99: 17 | E99: Retained Profit / Net Profit (% age) | F99: =IF(F95<>0,(F98/F95),"")*100 -> #VALUE! | G99: =IF(G95<>0,(G98/G95),"")*100 -> #VALUE! | H99: =IF(H95<>0,(H98/H95),"")*100 -> #VALUE! | I99: =IF(I95<>0,(I98/I95),"")*100 -> #VALUE! | J99: =IF(J95<>0,(J98/J95),"")*100 -> #VALUE! | K99: =IF(K95<>0,(K98/K95),"")*100 -> #VALUE! | L99: =IF(L95<>0,(L98/L95),"")*100 -> #VALUE! | M99: =IF(M95<>0,(M98/M95),"")*100 -> #VALUE! | ... BN99: =IF(BN95<>0,(BN98/BN95),"")*100 -> #VALUE!
A100: b2134858-f66e-4654-8e7f-65b9fc91210a | C100: 2 | E100: Balance Sheet
A101: 878de646-becc-492d-a157-3eecec0f591a | B101: b2134858-f66e-4654-8e7f-65b9fc91210a | C101: 2.1 | E101: Balance Sheet (Liabilities)
...
